{"Hours": [
  {
    "Year": 1977,
    "Month": 1,
    "Day": 1,
    "Hour": 1,
    "Dry-bulb": 12.2,
    "Dew Point": 11.1,
    "RH": 93
  },
  {
    "Year": 1977,
    "Month": 1,
    "Day": 1,
    "Hour": 2,
    "Dry-bulb": 12.2,
    "Dew Point": 10,
    "RH": 86
  },
  {
    "Year": 1977,
    "Month": 1,
    "Day": 1,
    "Hour": 3,
    "Dry-bulb": 11.7,
    "Dew Point": 9.4,
    "RH": 86
  },
  {
    "Year": 1977,
    "Month": 1,
    "Day": 1,
    "Hour": 4,
    "Dry-bulb": 11.1,
    "Dew Point": 9.4,
    "RH": 90
  },
  {
    "Year": 1977,
    "Month": 1,
    "Day": 1,
    "Hour": 5,
    "Dry-bulb": 11.1,
    "Dew Point": 8.9,
    "RH": 86
  },
  {
    "Year": 1977,
    "Month": 1,
    "Day": 1,
    "Hour": 6,
    "Dry-bulb": 10.6,
    "Dew Point": 9.4,
    "RH": 93
  },
  {
    "Year": 1977,
    "Month": 1,
    "Day": 1,
    "Hour": 7,
    "Dry-bulb": 10,
    "Dew Point": 9.4,
    "RH": 96
  },
  {
    "Year": 1977,
    "Month": 1,
    "Day": 1,
    "Hour": 8,
    "Dry-bulb": 10.6,
    "Dew Point": 9.4,
    "RH": 93
  },
  {
    "Year": 1977,
    "Month": 1,
    "Day": 1,
    "Hour": 9,
    "Dry-bulb": 12.8,
    "Dew Point": 10,
    "RH": 83
  },
  {
    "Year": 1977,
    "Month": 1,
    "Day": 1,
    "Hour": 10,
    "Dry-bulb": 13.3,
    "Dew Point": 10.6,
    "RH": 83
  },
  {
    "Year": 1977,
    "Month": 1,
    "Day": 1,
    "Hour": 11,
    "Dry-bulb": 13.9,
    "Dew Point": 10,
    "RH": 78
  },
  {
    "Year": 1977,
    "Month": 1,
    "Day": 1,
    "Hour": 12,
    "Dry-bulb": 14.4,
    "Dew Point": 10.6,
    "RH": 78
  },
  {
    "Year": 1977,
    "Month": 1,
    "Day": 1,
    "Hour": 13,
    "Dry-bulb": 15.6,
    "Dew Point": 10.6,
    "RH": 72
  },
  {
    "Year": 1977,
    "Month": 1,
    "Day": 1,
    "Hour": 14,
    "Dry-bulb": 15.6,
    "Dew Point": 11.7,
    "RH": 78
  },
  {
    "Year": 1977,
    "Month": 1,
    "Day": 1,
    "Hour": 15,
    "Dry-bulb": 16.7,
    "Dew Point": 12.2,
    "RH": 75
  },
  {
    "Year": 1977,
    "Month": 1,
    "Day": 1,
    "Hour": 16,
    "Dry-bulb": 16.7,
    "Dew Point": 12.2,
    "RH": 75
  },
  {
    "Year": 1977,
    "Month": 1,
    "Day": 1,
    "Hour": 17,
    "Dry-bulb": 15,
    "Dew Point": 11.7,
    "RH": 81
  },
  {
    "Year": 1977,
    "Month": 1,
    "Day": 1,
    "Hour": 18,
    "Dry-bulb": 15,
    "Dew Point": 11.1,
    "RH": 78
  },
  {
    "Year": 1977,
    "Month": 1,
    "Day": 1,
    "Hour": 19,
    "Dry-bulb": 14.4,
    "Dew Point": 11.7,
    "RH": 84
  },
  {
    "Year": 1977,
    "Month": 1,
    "Day": 1,
    "Hour": 20,
    "Dry-bulb": 14.4,
    "Dew Point": 11.7,
    "RH": 84
  },
  {
    "Year": 1977,
    "Month": 1,
    "Day": 1,
    "Hour": 21,
    "Dry-bulb": 13.9,
    "Dew Point": 11.1,
    "RH": 83
  },
  {
    "Year": 1977,
    "Month": 1,
    "Day": 1,
    "Hour": 22,
    "Dry-bulb": 12.8,
    "Dew Point": 10.6,
    "RH": 86
  },
  {
    "Year": 1977,
    "Month": 1,
    "Day": 1,
    "Hour": 23,
    "Dry-bulb": 12.8,
    "Dew Point": 10.6,
    "RH": 86
  },
  {
    "Year": 1977,
    "Month": 1,
    "Day": 1,
    "Hour": 24,
    "Dry-bulb": 12.2,
    "Dew Point": 10,
    "RH": 86
  },
  {
    "Year": 1977,
    "Month": 1,
    "Day": 2,
    "Hour": 1,
    "Dry-bulb": 12.2,
    "Dew Point": 10.6,
    "RH": 90
  },
  {
    "Year": 1977,
    "Month": 1,
    "Day": 2,
    "Hour": 2,
    "Dry-bulb": 11.7,
    "Dew Point": 10.6,
    "RH": 93
  },
  {
    "Year": 1977,
    "Month": 1,
    "Day": 2,
    "Hour": 3,
    "Dry-bulb": 11.1,
    "Dew Point": 10,
    "RH": 93
  },
  {
    "Year": 1977,
    "Month": 1,
    "Day": 2,
    "Hour": 4,
    "Dry-bulb": 11.7,
    "Dew Point": 11.1,
    "RH": 96
  },
  {
    "Year": 1977,
    "Month": 1,
    "Day": 2,
    "Hour": 5,
    "Dry-bulb": 11.7,
    "Dew Point": 10.6,
    "RH": 93
  },
  {
    "Year": 1977,
    "Month": 1,
    "Day": 2,
    "Hour": 6,
    "Dry-bulb": 11.7,
    "Dew Point": 10.6,
    "RH": 93
  },
  {
    "Year": 1977,
    "Month": 1,
    "Day": 2,
    "Hour": 7,
    "Dry-bulb": 11.1,
    "Dew Point": 11.1,
    "RH": 100
  },
  {
    "Year": 1977,
    "Month": 1,
    "Day": 2,
    "Hour": 8,
    "Dry-bulb": 11.1,
    "Dew Point": 10.6,
    "RH": 96
  },
  {
    "Year": 1977,
    "Month": 1,
    "Day": 2,
    "Hour": 9,
    "Dry-bulb": 11.7,
    "Dew Point": 11.1,
    "RH": 96
  },
  {
    "Year": 1977,
    "Month": 1,
    "Day": 2,
    "Hour": 10,
    "Dry-bulb": 12.2,
    "Dew Point": 11.1,
    "RH": 93
  },
  {
    "Year": 1977,
    "Month": 1,
    "Day": 2,
    "Hour": 11,
    "Dry-bulb": 12.8,
    "Dew Point": 11.7,
    "RH": 93
  },
  {
    "Year": 1977,
    "Month": 1,
    "Day": 2,
    "Hour": 12,
    "Dry-bulb": 12.8,
    "Dew Point": 12.8,
    "RH": 100
  },
  {
    "Year": 1977,
    "Month": 1,
    "Day": 2,
    "Hour": 13,
    "Dry-bulb": 12.8,
    "Dew Point": 12.8,
    "RH": 100
  },
  {
    "Year": 1977,
    "Month": 1,
    "Day": 2,
    "Hour": 14,
    "Dry-bulb": 12.8,
    "Dew Point": 12.8,
    "RH": 100
  },
  {
    "Year": 1977,
    "Month": 1,
    "Day": 2,
    "Hour": 15,
    "Dry-bulb": 12.8,
    "Dew Point": 12.8,
    "RH": 100
  },
  {
    "Year": 1977,
    "Month": 1,
    "Day": 2,
    "Hour": 16,
    "Dry-bulb": 12.8,
    "Dew Point": 12.8,
    "RH": 100
  },
  {
    "Year": 1977,
    "Month": 1,
    "Day": 2,
    "Hour": 17,
    "Dry-bulb": 12.8,
    "Dew Point": 12.8,
    "RH": 100
  },
  {
    "Year": 1977,
    "Month": 1,
    "Day": 2,
    "Hour": 18,
    "Dry-bulb": 12.8,
    "Dew Point": 12.8,
    "RH": 100
  },
  {
    "Year": 1977,
    "Month": 1,
    "Day": 2,
    "Hour": 19,
    "Dry-bulb": 12.8,
    "Dew Point": 12.8,
    "RH": 100
  },
  {
    "Year": 1977,
    "Month": 1,
    "Day": 2,
    "Hour": 20,
    "Dry-bulb": 12.8,
    "Dew Point": 12.8,
    "RH": 100
  },
  {
    "Year": 1977,
    "Month": 1,
    "Day": 2,
    "Hour": 21,
    "Dry-bulb": 12.8,
    "Dew Point": 12.8,
    "RH": 100
  },
  {
    "Year": 1977,
    "Month": 1,
    "Day": 2,
    "Hour": 22,
    "Dry-bulb": 12.8,
    "Dew Point": 12.8,
    "RH": 100
  },
  {
    "Year": 1977,
    "Month": 1,
    "Day": 2,
    "Hour": 23,
    "Dry-bulb": 12.8,
    "Dew Point": 12.8,
    "RH": 100
  },
  {
    "Year": 1977,
    "Month": 1,
    "Day": 2,
    "Hour": 24,
    "Dry-bulb": 12.8,
    "Dew Point": 12.8,
    "RH": 100
  },
  {
    "Year": 1977,
    "Month": 1,
    "Day": 3,
    "Hour": 1,
    "Dry-bulb": 13.9,
    "Dew Point": 13.9,
    "RH": 100
  },
  {
    "Year": 1977,
    "Month": 1,
    "Day": 3,
    "Hour": 2,
    "Dry-bulb": 13.9,
    "Dew Point": 13.3,
    "RH": 96
  },
  {
    "Year": 1977,
    "Month": 1,
    "Day": 3,
    "Hour": 3,
    "Dry-bulb": 13.3,
    "Dew Point": 11.7,
    "RH": 90
  },
  {
    "Year": 1977,
    "Month": 1,
    "Day": 3,
    "Hour": 4,
    "Dry-bulb": 12.8,
    "Dew Point": 8.3,
    "RH": 75
  },
  {
    "Year": 1977,
    "Month": 1,
    "Day": 3,
    "Hour": 5,
    "Dry-bulb": 11.7,
    "Dew Point": 5,
    "RH": 64
  },
  {
    "Year": 1977,
    "Month": 1,
    "Day": 3,
    "Hour": 6,
    "Dry-bulb": 11.7,
    "Dew Point": 3.3,
    "RH": 57
  },
  {
    "Year": 1977,
    "Month": 1,
    "Day": 3,
    "Hour": 7,
    "Dry-bulb": 11.7,
    "Dew Point": 1.7,
    "RH": 51
  },
  {
    "Year": 1977,
    "Month": 1,
    "Day": 3,
    "Hour": 8,
    "Dry-bulb": 11.7,
    "Dew Point": 2.2,
    "RH": 53
  },
  {
    "Year": 1977,
    "Month": 1,
    "Day": 3,
    "Hour": 9,
    "Dry-bulb": 12.8,
    "Dew Point": 2.2,
    "RH": 49
  },
  {
    "Year": 1977,
    "Month": 1,
    "Day": 3,
    "Hour": 10,
    "Dry-bulb": 14.4,
    "Dew Point": 2.2,
    "RH": 44
  },
  {
    "Year": 1977,
    "Month": 1,
    "Day": 3,
    "Hour": 11,
    "Dry-bulb": 14.4,
    "Dew Point": 4.4,
    "RH": 51
  },
  {
    "Year": 1977,
    "Month": 1,
    "Day": 3,
    "Hour": 12,
    "Dry-bulb": 15,
    "Dew Point": 3.9,
    "RH": 48
  },
  {
    "Year": 1977,
    "Month": 1,
    "Day": 3,
    "Hour": 13,
    "Dry-bulb": 15,
    "Dew Point": 5.6,
    "RH": 54
  },
  {
    "Year": 1977,
    "Month": 1,
    "Day": 3,
    "Hour": 14,
    "Dry-bulb": 15,
    "Dew Point": 6.7,
    "RH": 58
  },
  {
    "Year": 1977,
    "Month": 1,
    "Day": 3,
    "Hour": 15,
    "Dry-bulb": 15,
    "Dew Point": 7.2,
    "RH": 60
  },
  {
    "Year": 1977,
    "Month": 1,
    "Day": 3,
    "Hour": 16,
    "Dry-bulb": 16.1,
    "Dew Point": 7.8,
    "RH": 58
  },
  {
    "Year": 1977,
    "Month": 1,
    "Day": 3,
    "Hour": 17,
    "Dry-bulb": 15.6,
    "Dew Point": 8.3,
    "RH": 62
  },
  {
    "Year": 1977,
    "Month": 1,
    "Day": 3,
    "Hour": 18,
    "Dry-bulb": 15.6,
    "Dew Point": 7.8,
    "RH": 60
  },
  {
    "Year": 1977,
    "Month": 1,
    "Day": 3,
    "Hour": 19,
    "Dry-bulb": 15,
    "Dew Point": 8.9,
    "RH": 67
  },
  {
    "Year": 1977,
    "Month": 1,
    "Day": 3,
    "Hour": 20,
    "Dry-bulb": 13.9,
    "Dew Point": 2.8,
    "RH": 47
  },
  {
    "Year": 1977,
    "Month": 1,
    "Day": 3,
    "Hour": 21,
    "Dry-bulb": 13.3,
    "Dew Point": 2.8,
    "RH": 49
  },
  {
    "Year": 1977,
    "Month": 1,
    "Day": 3,
    "Hour": 22,
    "Dry-bulb": 12.8,
    "Dew Point": 2.8,
    "RH": 51
  },
  {
    "Year": 1977,
    "Month": 1,
    "Day": 3,
    "Hour": 23,
    "Dry-bulb": 12.2,
    "Dew Point": 2.8,
    "RH": 53
  },
  {
    "Year": 1977,
    "Month": 1,
    "Day": 3,
    "Hour": 24,
    "Dry-bulb": 11.7,
    "Dew Point": 2.8,
    "RH": 55
  },
  {
    "Year": 1977,
    "Month": 1,
    "Day": 4,
    "Hour": 1,
    "Dry-bulb": 10.6,
    "Dew Point": 2.2,
    "RH": 57
  },
  {
    "Year": 1977,
    "Month": 1,
    "Day": 4,
    "Hour": 2,
    "Dry-bulb": 9.4,
    "Dew Point": 3.3,
    "RH": 66
  },
  {
    "Year": 1977,
    "Month": 1,
    "Day": 4,
    "Hour": 3,
    "Dry-bulb": 7.2,
    "Dew Point": 3.9,
    "RH": 80
  },
  {
    "Year": 1977,
    "Month": 1,
    "Day": 4,
    "Hour": 4,
    "Dry-bulb": 7.2,
    "Dew Point": 3.9,
    "RH": 80
  },
  {
    "Year": 1977,
    "Month": 1,
    "Day": 4,
    "Hour": 5,
    "Dry-bulb": 7.8,
    "Dew Point": 3.3,
    "RH": 74
  },
  {
    "Year": 1977,
    "Month": 1,
    "Day": 4,
    "Hour": 6,
    "Dry-bulb": 7.2,
    "Dew Point": 2.2,
    "RH": 71
  },
  {
    "Year": 1977,
    "Month": 1,
    "Day": 4,
    "Hour": 7,
    "Dry-bulb": 7.8,
    "Dew Point": 2.2,
    "RH": 68
  },
  {
    "Year": 1977,
    "Month": 1,
    "Day": 4,
    "Hour": 8,
    "Dry-bulb": 8.9,
    "Dew Point": 3.3,
    "RH": 68
  },
  {
    "Year": 1977,
    "Month": 1,
    "Day": 4,
    "Hour": 9,
    "Dry-bulb": 10.6,
    "Dew Point": 4.4,
    "RH": 66
  },
  {
    "Year": 1977,
    "Month": 1,
    "Day": 4,
    "Hour": 10,
    "Dry-bulb": 12.8,
    "Dew Point": 6.1,
    "RH": 64
  },
  {
    "Year": 1977,
    "Month": 1,
    "Day": 4,
    "Hour": 11,
    "Dry-bulb": 13.9,
    "Dew Point": 8.3,
    "RH": 69
  },
  {
    "Year": 1977,
    "Month": 1,
    "Day": 4,
    "Hour": 12,
    "Dry-bulb": 15,
    "Dew Point": 7.8,
    "RH": 62
  },
  {
    "Year": 1977,
    "Month": 1,
    "Day": 4,
    "Hour": 13,
    "Dry-bulb": 15.6,
    "Dew Point": 6.7,
    "RH": 56
  },
  {
    "Year": 1977,
    "Month": 1,
    "Day": 4,
    "Hour": 14,
    "Dry-bulb": 15.6,
    "Dew Point": 7.8,
    "RH": 60
  },
  {
    "Year": 1977,
    "Month": 1,
    "Day": 4,
    "Hour": 15,
    "Dry-bulb": 15,
    "Dew Point": 8.3,
    "RH": 65
  },
  {
    "Year": 1977,
    "Month": 1,
    "Day": 4,
    "Hour": 16,
    "Dry-bulb": 15,
    "Dew Point": 7.2,
    "RH": 60
  },
  {
    "Year": 1977,
    "Month": 1,
    "Day": 4,
    "Hour": 17,
    "Dry-bulb": 13.9,
    "Dew Point": 7.8,
    "RH": 67
  },
  {
    "Year": 1977,
    "Month": 1,
    "Day": 4,
    "Hour": 18,
    "Dry-bulb": 12.8,
    "Dew Point": 7.2,
    "RH": 69
  },
  {
    "Year": 1977,
    "Month": 1,
    "Day": 4,
    "Hour": 19,
    "Dry-bulb": 11.7,
    "Dew Point": 7.2,
    "RH": 74
  },
  {
    "Year": 1977,
    "Month": 1,
    "Day": 4,
    "Hour": 20,
    "Dry-bulb": 12.2,
    "Dew Point": 5.6,
    "RH": 64
  },
  {
    "Year": 1977,
    "Month": 1,
    "Day": 4,
    "Hour": 21,
    "Dry-bulb": 12.2,
    "Dew Point": 5.6,
    "RH": 64
  },
  {
    "Year": 1977,
    "Month": 1,
    "Day": 4,
    "Hour": 22,
    "Dry-bulb": 11.7,
    "Dew Point": 7.2,
    "RH": 74
  },
  {
    "Year": 1977,
    "Month": 1,
    "Day": 4,
    "Hour": 23,
    "Dry-bulb": 10.6,
    "Dew Point": 6.7,
    "RH": 77
  },
  {
    "Year": 1977,
    "Month": 1,
    "Day": 4,
    "Hour": 24,
    "Dry-bulb": 10,
    "Dew Point": 6.7,
    "RH": 80
  },
  {
    "Year": 1977,
    "Month": 1,
    "Day": 5,
    "Hour": 1,
    "Dry-bulb": 10,
    "Dew Point": 6.7,
    "RH": 80
  },
  {
    "Year": 1977,
    "Month": 1,
    "Day": 5,
    "Hour": 2,
    "Dry-bulb": 8.9,
    "Dew Point": 6.1,
    "RH": 83
  },
  {
    "Year": 1977,
    "Month": 1,
    "Day": 5,
    "Hour": 3,
    "Dry-bulb": 8.3,
    "Dew Point": 6.1,
    "RH": 86
  },
  {
    "Year": 1977,
    "Month": 1,
    "Day": 5,
    "Hour": 4,
    "Dry-bulb": 8.3,
    "Dew Point": 6.1,
    "RH": 86
  },
  {
    "Year": 1977,
    "Month": 1,
    "Day": 5,
    "Hour": 5,
    "Dry-bulb": 7.8,
    "Dew Point": 5,
    "RH": 83
  },
  {
    "Year": 1977,
    "Month": 1,
    "Day": 5,
    "Hour": 6,
    "Dry-bulb": 7.8,
    "Dew Point": 5.6,
    "RH": 86
  },
  {
    "Year": 1977,
    "Month": 1,
    "Day": 5,
    "Hour": 7,
    "Dry-bulb": 9.4,
    "Dew Point": 6.1,
    "RH": 80
  },
  {
    "Year": 1977,
    "Month": 1,
    "Day": 5,
    "Hour": 8,
    "Dry-bulb": 8.3,
    "Dew Point": 6.7,
    "RH": 89
  },
  {
    "Year": 1977,
    "Month": 1,
    "Day": 5,
    "Hour": 9,
    "Dry-bulb": 9.4,
    "Dew Point": 7.2,
    "RH": 86
  },
  {
    "Year": 1977,
    "Month": 1,
    "Day": 5,
    "Hour": 10,
    "Dry-bulb": 10,
    "Dew Point": 7.8,
    "RH": 86
  },
  {
    "Year": 1977,
    "Month": 1,
    "Day": 5,
    "Hour": 11,
    "Dry-bulb": 11.7,
    "Dew Point": 8.3,
    "RH": 80
  },
  {
    "Year": 1977,
    "Month": 1,
    "Day": 5,
    "Hour": 12,
    "Dry-bulb": 13.3,
    "Dew Point": 8.9,
    "RH": 75
  },
  {
    "Year": 1977,
    "Month": 1,
    "Day": 5,
    "Hour": 13,
    "Dry-bulb": 13.3,
    "Dew Point": 7.8,
    "RH": 69
  },
  {
    "Year": 1977,
    "Month": 1,
    "Day": 5,
    "Hour": 14,
    "Dry-bulb": 13.3,
    "Dew Point": 6.7,
    "RH": 64
  },
  {
    "Year": 1977,
    "Month": 1,
    "Day": 5,
    "Hour": 15,
    "Dry-bulb": 13.3,
    "Dew Point": 8.3,
    "RH": 72
  },
  {
    "Year": 1977,
    "Month": 1,
    "Day": 5,
    "Hour": 16,
    "Dry-bulb": 11.1,
    "Dew Point": 8.9,
    "RH": 86
  },
  {
    "Year": 1977,
    "Month": 1,
    "Day": 5,
    "Hour": 17,
    "Dry-bulb": 10.6,
    "Dew Point": 8.9,
    "RH": 90
  },
  {
    "Year": 1977,
    "Month": 1,
    "Day": 5,
    "Hour": 18,
    "Dry-bulb": 10.6,
    "Dew Point": 8.9,
    "RH": 90
  },
  {
    "Year": 1977,
    "Month": 1,
    "Day": 5,
    "Hour": 19,
    "Dry-bulb": 10.6,
    "Dew Point": 9.4,
    "RH": 93
  },
  {
    "Year": 1977,
    "Month": 1,
    "Day": 5,
    "Hour": 20,
    "Dry-bulb": 10,
    "Dew Point": 9.4,
    "RH": 96
  },
  {
    "Year": 1977,
    "Month": 1,
    "Day": 5,
    "Hour": 21,
    "Dry-bulb": 9.4,
    "Dew Point": 8.9,
    "RH": 96
  },
  {
    "Year": 1977,
    "Month": 1,
    "Day": 5,
    "Hour": 22,
    "Dry-bulb": 8.3,
    "Dew Point": 7.8,
    "RH": 96
  },
  {
    "Year": 1977,
    "Month": 1,
    "Day": 5,
    "Hour": 23,
    "Dry-bulb": 8.3,
    "Dew Point": 7.8,
    "RH": 96
  },
  {
    "Year": 1977,
    "Month": 1,
    "Day": 5,
    "Hour": 24,
    "Dry-bulb": 8.3,
    "Dew Point": 7.2,
    "RH": 93
  },
  {
    "Year": 1977,
    "Month": 1,
    "Day": 6,
    "Hour": 1,
    "Dry-bulb": 8.3,
    "Dew Point": 7.8,
    "RH": 96
  },
  {
    "Year": 1977,
    "Month": 1,
    "Day": 6,
    "Hour": 2,
    "Dry-bulb": 8.3,
    "Dew Point": 8.3,
    "RH": 100
  },
  {
    "Year": 1977,
    "Month": 1,
    "Day": 6,
    "Hour": 3,
    "Dry-bulb": 8.3,
    "Dew Point": 7.8,
    "RH": 96
  },
  {
    "Year": 1977,
    "Month": 1,
    "Day": 6,
    "Hour": 4,
    "Dry-bulb": 8.3,
    "Dew Point": 7.8,
    "RH": 96
  },
  {
    "Year": 1977,
    "Month": 1,
    "Day": 6,
    "Hour": 5,
    "Dry-bulb": 8.3,
    "Dew Point": 7.8,
    "RH": 96
  },
  {
    "Year": 1977,
    "Month": 1,
    "Day": 6,
    "Hour": 6,
    "Dry-bulb": 8.3,
    "Dew Point": 7.8,
    "RH": 96
  },
  {
    "Year": 1977,
    "Month": 1,
    "Day": 6,
    "Hour": 7,
    "Dry-bulb": 8.3,
    "Dew Point": 7.2,
    "RH": 93
  },
  {
    "Year": 1977,
    "Month": 1,
    "Day": 6,
    "Hour": 8,
    "Dry-bulb": 8.3,
    "Dew Point": 7.2,
    "RH": 93
  },
  {
    "Year": 1977,
    "Month": 1,
    "Day": 6,
    "Hour": 9,
    "Dry-bulb": 8.3,
    "Dew Point": 7.8,
    "RH": 96
  },
  {
    "Year": 1977,
    "Month": 1,
    "Day": 6,
    "Hour": 10,
    "Dry-bulb": 8.3,
    "Dew Point": 8.3,
    "RH": 100
  },
  {
    "Year": 1977,
    "Month": 1,
    "Day": 6,
    "Hour": 11,
    "Dry-bulb": 8.9,
    "Dew Point": 8.9,
    "RH": 100
  },
  {
    "Year": 1977,
    "Month": 1,
    "Day": 6,
    "Hour": 12,
    "Dry-bulb": 10.6,
    "Dew Point": 10,
    "RH": 96
  },
  {
    "Year": 1977,
    "Month": 1,
    "Day": 6,
    "Hour": 13,
    "Dry-bulb": 10.6,
    "Dew Point": 10,
    "RH": 96
  },
  {
    "Year": 1977,
    "Month": 1,
    "Day": 6,
    "Hour": 14,
    "Dry-bulb": 10.6,
    "Dew Point": 10,
    "RH": 96
  },
  {
    "Year": 1977,
    "Month": 1,
    "Day": 6,
    "Hour": 15,
    "Dry-bulb": 11.1,
    "Dew Point": 10.6,
    "RH": 96
  },
  {
    "Year": 1977,
    "Month": 1,
    "Day": 6,
    "Hour": 16,
    "Dry-bulb": 11.1,
    "Dew Point": 9.4,
    "RH": 90
  },
  {
    "Year": 1977,
    "Month": 1,
    "Day": 6,
    "Hour": 17,
    "Dry-bulb": 11.1,
    "Dew Point": 10,
    "RH": 93
  },
  {
    "Year": 1977,
    "Month": 1,
    "Day": 6,
    "Hour": 18,
    "Dry-bulb": 11.1,
    "Dew Point": 10,
    "RH": 93
  },
  {
    "Year": 1977,
    "Month": 1,
    "Day": 6,
    "Hour": 19,
    "Dry-bulb": 10.6,
    "Dew Point": 10,
    "RH": 96
  },
  {
    "Year": 1977,
    "Month": 1,
    "Day": 6,
    "Hour": 20,
    "Dry-bulb": 10.6,
    "Dew Point": 10,
    "RH": 96
  },
  {
    "Year": 1977,
    "Month": 1,
    "Day": 6,
    "Hour": 21,
    "Dry-bulb": 11.1,
    "Dew Point": 10,
    "RH": 93
  },
  {
    "Year": 1977,
    "Month": 1,
    "Day": 6,
    "Hour": 22,
    "Dry-bulb": 11.1,
    "Dew Point": 10,
    "RH": 93
  },
  {
    "Year": 1977,
    "Month": 1,
    "Day": 6,
    "Hour": 23,
    "Dry-bulb": 11.1,
    "Dew Point": 10,
    "RH": 93
  },
  {
    "Year": 1977,
    "Month": 1,
    "Day": 6,
    "Hour": 24,
    "Dry-bulb": 11.1,
    "Dew Point": 9.4,
    "RH": 90
  },
  {
    "Year": 1977,
    "Month": 1,
    "Day": 7,
    "Hour": 1,
    "Dry-bulb": 10.6,
    "Dew Point": 10,
    "RH": 96
  },
  {
    "Year": 1977,
    "Month": 1,
    "Day": 7,
    "Hour": 2,
    "Dry-bulb": 10.6,
    "Dew Point": 10,
    "RH": 96
  },
  {
    "Year": 1977,
    "Month": 1,
    "Day": 7,
    "Hour": 3,
    "Dry-bulb": 10.6,
    "Dew Point": 10.6,
    "RH": 100
  },
  {
    "Year": 1977,
    "Month": 1,
    "Day": 7,
    "Hour": 4,
    "Dry-bulb": 10.6,
    "Dew Point": 10.6,
    "RH": 100
  },
  {
    "Year": 1977,
    "Month": 1,
    "Day": 7,
    "Hour": 5,
    "Dry-bulb": 10.6,
    "Dew Point": 10.6,
    "RH": 100
  },
  {
    "Year": 1977,
    "Month": 1,
    "Day": 7,
    "Hour": 6,
    "Dry-bulb": 10.6,
    "Dew Point": 10.6,
    "RH": 100
  },
  {
    "Year": 1977,
    "Month": 1,
    "Day": 7,
    "Hour": 7,
    "Dry-bulb": 11.1,
    "Dew Point": 10.6,
    "RH": 96
  },
  {
    "Year": 1977,
    "Month": 1,
    "Day": 7,
    "Hour": 8,
    "Dry-bulb": 11.1,
    "Dew Point": 10.6,
    "RH": 96
  },
  {
    "Year": 1977,
    "Month": 1,
    "Day": 7,
    "Hour": 9,
    "Dry-bulb": 11.1,
    "Dew Point": 11.1,
    "RH": 100
  },
  {
    "Year": 1977,
    "Month": 1,
    "Day": 7,
    "Hour": 10,
    "Dry-bulb": 11.1,
    "Dew Point": 11.1,
    "RH": 100
  },
  {
    "Year": 1977,
    "Month": 1,
    "Day": 7,
    "Hour": 11,
    "Dry-bulb": 11.7,
    "Dew Point": 10.6,
    "RH": 93
  },
  {
    "Year": 1977,
    "Month": 1,
    "Day": 7,
    "Hour": 12,
    "Dry-bulb": 11.1,
    "Dew Point": 10.6,
    "RH": 96
  },
  {
    "Year": 1977,
    "Month": 1,
    "Day": 7,
    "Hour": 13,
    "Dry-bulb": 11.1,
    "Dew Point": 9.4,
    "RH": 90
  },
  {
    "Year": 1977,
    "Month": 1,
    "Day": 7,
    "Hour": 14,
    "Dry-bulb": 10,
    "Dew Point": 9.4,
    "RH": 96
  },
  {
    "Year": 1977,
    "Month": 1,
    "Day": 7,
    "Hour": 15,
    "Dry-bulb": 10,
    "Dew Point": 8.9,
    "RH": 93
  },
  {
    "Year": 1977,
    "Month": 1,
    "Day": 7,
    "Hour": 16,
    "Dry-bulb": 11.1,
    "Dew Point": 8.3,
    "RH": 83
  },
  {
    "Year": 1977,
    "Month": 1,
    "Day": 7,
    "Hour": 17,
    "Dry-bulb": 11.1,
    "Dew Point": 8.3,
    "RH": 83
  },
  {
    "Year": 1977,
    "Month": 1,
    "Day": 7,
    "Hour": 18,
    "Dry-bulb": 10.6,
    "Dew Point": 7.8,
    "RH": 83
  },
  {
    "Year": 1977,
    "Month": 1,
    "Day": 7,
    "Hour": 19,
    "Dry-bulb": 10.6,
    "Dew Point": 7.8,
    "RH": 83
  },
  {
    "Year": 1977,
    "Month": 1,
    "Day": 7,
    "Hour": 20,
    "Dry-bulb": 10.6,
    "Dew Point": 7.2,
    "RH": 80
  },
  {
    "Year": 1977,
    "Month": 1,
    "Day": 7,
    "Hour": 21,
    "Dry-bulb": 10.6,
    "Dew Point": 6.7,
    "RH": 77
  },
  {
    "Year": 1977,
    "Month": 1,
    "Day": 7,
    "Hour": 22,
    "Dry-bulb": 10.6,
    "Dew Point": 5,
    "RH": 69
  },
  {
    "Year": 1977,
    "Month": 1,
    "Day": 7,
    "Hour": 23,
    "Dry-bulb": 11.1,
    "Dew Point": 3.9,
    "RH": 61
  },
  {
    "Year": 1977,
    "Month": 1,
    "Day": 7,
    "Hour": 24,
    "Dry-bulb": 11.1,
    "Dew Point": 3.9,
    "RH": 61
  },
  {
    "Year": 1977,
    "Month": 1,
    "Day": 8,
    "Hour": 1,
    "Dry-bulb": 10.6,
    "Dew Point": 4.4,
    "RH": 66
  },
  {
    "Year": 1977,
    "Month": 1,
    "Day": 8,
    "Hour": 2,
    "Dry-bulb": 9.4,
    "Dew Point": 6.1,
    "RH": 80
  },
  {
    "Year": 1977,
    "Month": 1,
    "Day": 8,
    "Hour": 3,
    "Dry-bulb": 7.2,
    "Dew Point": 6.1,
    "RH": 93
  },
  {
    "Year": 1977,
    "Month": 1,
    "Day": 8,
    "Hour": 4,
    "Dry-bulb": 6.7,
    "Dew Point": 5.6,
    "RH": 93
  },
  {
    "Year": 1977,
    "Month": 1,
    "Day": 8,
    "Hour": 5,
    "Dry-bulb": 6.7,
    "Dew Point": 6.1,
    "RH": 96
  },
  {
    "Year": 1977,
    "Month": 1,
    "Day": 8,
    "Hour": 6,
    "Dry-bulb": 5.6,
    "Dew Point": 4.4,
    "RH": 93
  },
  {
    "Year": 1977,
    "Month": 1,
    "Day": 8,
    "Hour": 7,
    "Dry-bulb": 5.6,
    "Dew Point": 5.6,
    "RH": 100
  },
  {
    "Year": 1977,
    "Month": 1,
    "Day": 8,
    "Hour": 8,
    "Dry-bulb": 6.7,
    "Dew Point": 6.7,
    "RH": 100
  },
  {
    "Year": 1977,
    "Month": 1,
    "Day": 8,
    "Hour": 9,
    "Dry-bulb": 9.4,
    "Dew Point": 8.3,
    "RH": 93
  },
  {
    "Year": 1977,
    "Month": 1,
    "Day": 8,
    "Hour": 10,
    "Dry-bulb": 11.7,
    "Dew Point": 8.9,
    "RH": 83
  },
  {
    "Year": 1977,
    "Month": 1,
    "Day": 8,
    "Hour": 11,
    "Dry-bulb": 14.4,
    "Dew Point": 4.4,
    "RH": 51
  },
  {
    "Year": 1977,
    "Month": 1,
    "Day": 8,
    "Hour": 12,
    "Dry-bulb": 15,
    "Dew Point": 6.7,
    "RH": 58
  },
  {
    "Year": 1977,
    "Month": 1,
    "Day": 8,
    "Hour": 13,
    "Dry-bulb": 15,
    "Dew Point": 5.6,
    "RH": 54
  },
  {
    "Year": 1977,
    "Month": 1,
    "Day": 8,
    "Hour": 14,
    "Dry-bulb": 15,
    "Dew Point": 7.2,
    "RH": 60
  },
  {
    "Year": 1977,
    "Month": 1,
    "Day": 8,
    "Hour": 15,
    "Dry-bulb": 15.6,
    "Dew Point": 7.2,
    "RH": 58
  },
  {
    "Year": 1977,
    "Month": 1,
    "Day": 8,
    "Hour": 16,
    "Dry-bulb": 15.6,
    "Dew Point": 7.2,
    "RH": 58
  },
  {
    "Year": 1977,
    "Month": 1,
    "Day": 8,
    "Hour": 17,
    "Dry-bulb": 15,
    "Dew Point": 6.1,
    "RH": 56
  },
  {
    "Year": 1977,
    "Month": 1,
    "Day": 8,
    "Hour": 18,
    "Dry-bulb": 13.3,
    "Dew Point": 7.2,
    "RH": 67
  },
  {
    "Year": 1977,
    "Month": 1,
    "Day": 8,
    "Hour": 19,
    "Dry-bulb": 13.3,
    "Dew Point": 0,
    "RH": 40
  },
  {
    "Year": 1977,
    "Month": 1,
    "Day": 8,
    "Hour": 20,
    "Dry-bulb": 12.8,
    "Dew Point": -0.6,
    "RH": 40
  },
  {
    "Year": 1977,
    "Month": 1,
    "Day": 8,
    "Hour": 21,
    "Dry-bulb": 11.7,
    "Dew Point": -1.1,
    "RH": 41
  },
  {
    "Year": 1977,
    "Month": 1,
    "Day": 8,
    "Hour": 22,
    "Dry-bulb": 9.4,
    "Dew Point": 1.1,
    "RH": 56
  },
  {
    "Year": 1977,
    "Month": 1,
    "Day": 8,
    "Hour": 23,
    "Dry-bulb": 9.4,
    "Dew Point": 1.7,
    "RH": 59
  },
  {
    "Year": 1977,
    "Month": 1,
    "Day": 8,
    "Hour": 24,
    "Dry-bulb": 9.4,
    "Dew Point": 3.3,
    "RH": 66
  },
  {
    "Year": 1977,
    "Month": 1,
    "Day": 9,
    "Hour": 1,
    "Dry-bulb": 8.3,
    "Dew Point": 2.8,
    "RH": 68
  },
  {
    "Year": 1977,
    "Month": 1,
    "Day": 9,
    "Hour": 2,
    "Dry-bulb": 7.8,
    "Dew Point": 2.2,
    "RH": 68
  },
  {
    "Year": 1977,
    "Month": 1,
    "Day": 9,
    "Hour": 3,
    "Dry-bulb": 7.8,
    "Dew Point": 2.2,
    "RH": 68
  },
  {
    "Year": 1977,
    "Month": 1,
    "Day": 9,
    "Hour": 4,
    "Dry-bulb": 7.8,
    "Dew Point": 2.2,
    "RH": 68
  },
  {
    "Year": 1977,
    "Month": 1,
    "Day": 9,
    "Hour": 5,
    "Dry-bulb": 6.1,
    "Dew Point": 2.2,
    "RH": 76
  },
  {
    "Year": 1977,
    "Month": 1,
    "Day": 9,
    "Hour": 6,
    "Dry-bulb": 7.2,
    "Dew Point": 1.7,
    "RH": 68
  },
  {
    "Year": 1977,
    "Month": 1,
    "Day": 9,
    "Hour": 7,
    "Dry-bulb": 7.2,
    "Dew Point": 1.7,
    "RH": 68
  },
  {
    "Year": 1977,
    "Month": 1,
    "Day": 9,
    "Hour": 8,
    "Dry-bulb": 7.8,
    "Dew Point": 2.2,
    "RH": 68
  },
  {
    "Year": 1977,
    "Month": 1,
    "Day": 9,
    "Hour": 9,
    "Dry-bulb": 10.6,
    "Dew Point": 2.2,
    "RH": 57
  },
  {
    "Year": 1977,
    "Month": 1,
    "Day": 9,
    "Hour": 10,
    "Dry-bulb": 12.8,
    "Dew Point": 3.9,
    "RH": 55
  },
  {
    "Year": 1977,
    "Month": 1,
    "Day": 9,
    "Hour": 11,
    "Dry-bulb": 14.4,
    "Dew Point": 5.6,
    "RH": 55
  },
  {
    "Year": 1977,
    "Month": 1,
    "Day": 9,
    "Hour": 12,
    "Dry-bulb": 15.6,
    "Dew Point": 7.2,
    "RH": 58
  },
  {
    "Year": 1977,
    "Month": 1,
    "Day": 9,
    "Hour": 13,
    "Dry-bulb": 16.7,
    "Dew Point": 7.8,
    "RH": 56
  },
  {
    "Year": 1977,
    "Month": 1,
    "Day": 9,
    "Hour": 14,
    "Dry-bulb": 16.7,
    "Dew Point": 7.8,
    "RH": 56
  },
  {
    "Year": 1977,
    "Month": 1,
    "Day": 9,
    "Hour": 15,
    "Dry-bulb": 16.7,
    "Dew Point": 9.4,
    "RH": 63
  },
  {
    "Year": 1977,
    "Month": 1,
    "Day": 9,
    "Hour": 16,
    "Dry-bulb": 16.1,
    "Dew Point": 9.4,
    "RH": 65
  },
  {
    "Year": 1977,
    "Month": 1,
    "Day": 9,
    "Hour": 17,
    "Dry-bulb": 14.4,
    "Dew Point": 8.9,
    "RH": 70
  },
  {
    "Year": 1977,
    "Month": 1,
    "Day": 9,
    "Hour": 18,
    "Dry-bulb": 13.3,
    "Dew Point": 8.3,
    "RH": 72
  },
  {
    "Year": 1977,
    "Month": 1,
    "Day": 9,
    "Hour": 19,
    "Dry-bulb": 12.8,
    "Dew Point": 8.9,
    "RH": 77
  },
  {
    "Year": 1977,
    "Month": 1,
    "Day": 9,
    "Hour": 20,
    "Dry-bulb": 12.2,
    "Dew Point": 2.2,
    "RH": 51
  },
  {
    "Year": 1977,
    "Month": 1,
    "Day": 9,
    "Hour": 21,
    "Dry-bulb": 12.2,
    "Dew Point": 1.7,
    "RH": 49
  },
  {
    "Year": 1977,
    "Month": 1,
    "Day": 9,
    "Hour": 22,
    "Dry-bulb": 12.2,
    "Dew Point": 1.1,
    "RH": 47
  },
  {
    "Year": 1977,
    "Month": 1,
    "Day": 9,
    "Hour": 23,
    "Dry-bulb": 10.6,
    "Dew Point": 1.7,
    "RH": 54
  },
  {
    "Year": 1977,
    "Month": 1,
    "Day": 9,
    "Hour": 24,
    "Dry-bulb": 10,
    "Dew Point": 1.7,
    "RH": 57
  },
  {
    "Year": 1977,
    "Month": 1,
    "Day": 10,
    "Hour": 1,
    "Dry-bulb": 8.3,
    "Dew Point": 1.7,
    "RH": 63
  },
  {
    "Year": 1977,
    "Month": 1,
    "Day": 10,
    "Hour": 2,
    "Dry-bulb": 8.3,
    "Dew Point": 2.2,
    "RH": 66
  },
  {
    "Year": 1977,
    "Month": 1,
    "Day": 10,
    "Hour": 3,
    "Dry-bulb": 7.8,
    "Dew Point": 2.2,
    "RH": 68
  },
  {
    "Year": 1977,
    "Month": 1,
    "Day": 10,
    "Hour": 4,
    "Dry-bulb": 7.2,
    "Dew Point": 1.7,
    "RH": 68
  },
  {
    "Year": 1977,
    "Month": 1,
    "Day": 10,
    "Hour": 5,
    "Dry-bulb": 6.1,
    "Dew Point": 1.1,
    "RH": 71
  },
  {
    "Year": 1977,
    "Month": 1,
    "Day": 10,
    "Hour": 6,
    "Dry-bulb": 6.1,
    "Dew Point": 0.6,
    "RH": 68
  },
  {
    "Year": 1977,
    "Month": 1,
    "Day": 10,
    "Hour": 7,
    "Dry-bulb": 6.1,
    "Dew Point": -0.6,
    "RH": 63
  },
  {
    "Year": 1977,
    "Month": 1,
    "Day": 10,
    "Hour": 8,
    "Dry-bulb": 8.3,
    "Dew Point": 1.1,
    "RH": 61
  },
  {
    "Year": 1977,
    "Month": 1,
    "Day": 10,
    "Hour": 9,
    "Dry-bulb": 10.6,
    "Dew Point": 1.7,
    "RH": 54
  },
  {
    "Year": 1977,
    "Month": 1,
    "Day": 10,
    "Hour": 10,
    "Dry-bulb": 13.3,
    "Dew Point": 2.2,
    "RH": 47
  },
  {
    "Year": 1977,
    "Month": 1,
    "Day": 10,
    "Hour": 11,
    "Dry-bulb": 15,
    "Dew Point": 6.1,
    "RH": 56
  },
  {
    "Year": 1977,
    "Month": 1,
    "Day": 10,
    "Hour": 12,
    "Dry-bulb": 15,
    "Dew Point": 9.4,
    "RH": 70
  },
  {
    "Year": 1977,
    "Month": 1,
    "Day": 10,
    "Hour": 13,
    "Dry-bulb": 15,
    "Dew Point": 9.4,
    "RH": 70
  },
  {
    "Year": 1977,
    "Month": 1,
    "Day": 10,
    "Hour": 14,
    "Dry-bulb": 15.6,
    "Dew Point": 8.9,
    "RH": 65
  },
  {
    "Year": 1977,
    "Month": 1,
    "Day": 10,
    "Hour": 15,
    "Dry-bulb": 15.6,
    "Dew Point": 8.3,
    "RH": 62
  },
  {
    "Year": 1977,
    "Month": 1,
    "Day": 10,
    "Hour": 16,
    "Dry-bulb": 15,
    "Dew Point": 8.3,
    "RH": 65
  },
  {
    "Year": 1977,
    "Month": 1,
    "Day": 10,
    "Hour": 17,
    "Dry-bulb": 13.9,
    "Dew Point": 7.8,
    "RH": 67
  },
  {
    "Year": 1977,
    "Month": 1,
    "Day": 10,
    "Hour": 18,
    "Dry-bulb": 12.2,
    "Dew Point": 7.8,
    "RH": 75
  },
  {
    "Year": 1977,
    "Month": 1,
    "Day": 10,
    "Hour": 19,
    "Dry-bulb": 12.2,
    "Dew Point": 7.8,
    "RH": 75
  },
  {
    "Year": 1977,
    "Month": 1,
    "Day": 10,
    "Hour": 20,
    "Dry-bulb": 11.7,
    "Dew Point": 8.9,
    "RH": 83
  },
  {
    "Year": 1977,
    "Month": 1,
    "Day": 10,
    "Hour": 21,
    "Dry-bulb": 11.7,
    "Dew Point": 8.3,
    "RH": 80
  },
  {
    "Year": 1977,
    "Month": 1,
    "Day": 10,
    "Hour": 22,
    "Dry-bulb": 11.1,
    "Dew Point": 8.3,
    "RH": 83
  },
  {
    "Year": 1977,
    "Month": 1,
    "Day": 10,
    "Hour": 23,
    "Dry-bulb": 10,
    "Dew Point": 4.4,
    "RH": 69
  },
  {
    "Year": 1977,
    "Month": 1,
    "Day": 10,
    "Hour": 24,
    "Dry-bulb": 9.4,
    "Dew Point": 3.9,
    "RH": 69
  },
  {
    "Year": 1977,
    "Month": 1,
    "Day": 11,
    "Hour": 1,
    "Dry-bulb": 8.3,
    "Dew Point": 4.4,
    "RH": 77
  },
  {
    "Year": 1977,
    "Month": 1,
    "Day": 11,
    "Hour": 2,
    "Dry-bulb": 7.2,
    "Dew Point": 4.4,
    "RH": 83
  },
  {
    "Year": 1977,
    "Month": 1,
    "Day": 11,
    "Hour": 3,
    "Dry-bulb": 6.1,
    "Dew Point": 4.4,
    "RH": 89
  },
  {
    "Year": 1977,
    "Month": 1,
    "Day": 11,
    "Hour": 4,
    "Dry-bulb": 6.1,
    "Dew Point": 3.9,
    "RH": 86
  },
  {
    "Year": 1977,
    "Month": 1,
    "Day": 11,
    "Hour": 5,
    "Dry-bulb": 7.2,
    "Dew Point": 3.3,
    "RH": 77
  },
  {
    "Year": 1977,
    "Month": 1,
    "Day": 11,
    "Hour": 6,
    "Dry-bulb": 6.1,
    "Dew Point": 3.3,
    "RH": 83
  },
  {
    "Year": 1977,
    "Month": 1,
    "Day": 11,
    "Hour": 7,
    "Dry-bulb": 6.1,
    "Dew Point": 1.7,
    "RH": 73
  },
  {
    "Year": 1977,
    "Month": 1,
    "Day": 11,
    "Hour": 8,
    "Dry-bulb": 7.2,
    "Dew Point": 3.3,
    "RH": 77
  },
  {
    "Year": 1977,
    "Month": 1,
    "Day": 11,
    "Hour": 9,
    "Dry-bulb": 11.7,
    "Dew Point": 3.3,
    "RH": 57
  },
  {
    "Year": 1977,
    "Month": 1,
    "Day": 11,
    "Hour": 10,
    "Dry-bulb": 14.4,
    "Dew Point": 3.3,
    "RH": 48
  },
  {
    "Year": 1977,
    "Month": 1,
    "Day": 11,
    "Hour": 11,
    "Dry-bulb": 17.2,
    "Dew Point": 2.2,
    "RH": 37
  },
  {
    "Year": 1977,
    "Month": 1,
    "Day": 11,
    "Hour": 12,
    "Dry-bulb": 18.3,
    "Dew Point": 2.8,
    "RH": 36
  },
  {
    "Year": 1977,
    "Month": 1,
    "Day": 11,
    "Hour": 13,
    "Dry-bulb": 20.6,
    "Dew Point": 3.3,
    "RH": 32
  },
  {
    "Year": 1977,
    "Month": 1,
    "Day": 11,
    "Hour": 14,
    "Dry-bulb": 20,
    "Dew Point": 3.9,
    "RH": 35
  },
  {
    "Year": 1977,
    "Month": 1,
    "Day": 11,
    "Hour": 15,
    "Dry-bulb": 17.2,
    "Dew Point": 9.4,
    "RH": 60
  },
  {
    "Year": 1977,
    "Month": 1,
    "Day": 11,
    "Hour": 16,
    "Dry-bulb": 16.7,
    "Dew Point": 10.6,
    "RH": 67
  },
  {
    "Year": 1977,
    "Month": 1,
    "Day": 11,
    "Hour": 17,
    "Dry-bulb": 15.6,
    "Dew Point": 10.6,
    "RH": 72
  },
  {
    "Year": 1977,
    "Month": 1,
    "Day": 11,
    "Hour": 18,
    "Dry-bulb": 15,
    "Dew Point": 9.4,
    "RH": 70
  },
  {
    "Year": 1977,
    "Month": 1,
    "Day": 11,
    "Hour": 19,
    "Dry-bulb": 15,
    "Dew Point": 1.1,
    "RH": 39
  },
  {
    "Year": 1977,
    "Month": 1,
    "Day": 11,
    "Hour": 20,
    "Dry-bulb": 15,
    "Dew Point": 0.6,
    "RH": 38
  },
  {
    "Year": 1977,
    "Month": 1,
    "Day": 11,
    "Hour": 21,
    "Dry-bulb": 14.4,
    "Dew Point": 1.1,
    "RH": 41
  },
  {
    "Year": 1977,
    "Month": 1,
    "Day": 11,
    "Hour": 22,
    "Dry-bulb": 13.3,
    "Dew Point": 1.7,
    "RH": 45
  },
  {
    "Year": 1977,
    "Month": 1,
    "Day": 11,
    "Hour": 23,
    "Dry-bulb": 13.3,
    "Dew Point": 1.7,
    "RH": 45
  },
  {
    "Year": 1977,
    "Month": 1,
    "Day": 11,
    "Hour": 24,
    "Dry-bulb": 11.7,
    "Dew Point": 1.1,
    "RH": 49
  },
  {
    "Year": 1977,
    "Month": 1,
    "Day": 12,
    "Hour": 1,
    "Dry-bulb": 11.1,
    "Dew Point": 1.7,
    "RH": 53
  },
  {
    "Year": 1977,
    "Month": 1,
    "Day": 12,
    "Hour": 2,
    "Dry-bulb": 8.9,
    "Dew Point": 2.2,
    "RH": 63
  },
  {
    "Year": 1977,
    "Month": 1,
    "Day": 12,
    "Hour": 3,
    "Dry-bulb": 9.4,
    "Dew Point": 2.2,
    "RH": 61
  },
  {
    "Year": 1977,
    "Month": 1,
    "Day": 12,
    "Hour": 4,
    "Dry-bulb": 9.4,
    "Dew Point": 2.2,
    "RH": 61
  },
  {
    "Year": 1977,
    "Month": 1,
    "Day": 12,
    "Hour": 5,
    "Dry-bulb": 7.8,
    "Dew Point": 2.8,
    "RH": 71
  },
  {
    "Year": 1977,
    "Month": 1,
    "Day": 12,
    "Hour": 6,
    "Dry-bulb": 8.3,
    "Dew Point": 2.2,
    "RH": 66
  },
  {
    "Year": 1977,
    "Month": 1,
    "Day": 12,
    "Hour": 7,
    "Dry-bulb": 8.9,
    "Dew Point": 2.8,
    "RH": 66
  },
  {
    "Year": 1977,
    "Month": 1,
    "Day": 12,
    "Hour": 8,
    "Dry-bulb": 8.9,
    "Dew Point": 3.3,
    "RH": 68
  },
  {
    "Year": 1977,
    "Month": 1,
    "Day": 12,
    "Hour": 9,
    "Dry-bulb": 11.7,
    "Dew Point": 3.3,
    "RH": 57
  },
  {
    "Year": 1977,
    "Month": 1,
    "Day": 12,
    "Hour": 10,
    "Dry-bulb": 12.8,
    "Dew Point": 6.1,
    "RH": 64
  },
  {
    "Year": 1977,
    "Month": 1,
    "Day": 12,
    "Hour": 11,
    "Dry-bulb": 15.6,
    "Dew Point": 11.1,
    "RH": 75
  },
  {
    "Year": 1977,
    "Month": 1,
    "Day": 12,
    "Hour": 12,
    "Dry-bulb": 16.1,
    "Dew Point": 11.7,
    "RH": 75
  },
  {
    "Year": 1977,
    "Month": 1,
    "Day": 12,
    "Hour": 13,
    "Dry-bulb": 17.2,
    "Dew Point": 10.6,
    "RH": 65
  },
  {
    "Year": 1977,
    "Month": 1,
    "Day": 12,
    "Hour": 14,
    "Dry-bulb": 17.8,
    "Dew Point": 11.1,
    "RH": 65
  },
  {
    "Year": 1977,
    "Month": 1,
    "Day": 12,
    "Hour": 15,
    "Dry-bulb": 16.7,
    "Dew Point": 10.6,
    "RH": 67
  },
  {
    "Year": 1977,
    "Month": 1,
    "Day": 12,
    "Hour": 16,
    "Dry-bulb": 16.1,
    "Dew Point": 10.6,
    "RH": 70
  },
  {
    "Year": 1977,
    "Month": 1,
    "Day": 12,
    "Hour": 17,
    "Dry-bulb": 15.6,
    "Dew Point": 11.7,
    "RH": 78
  },
  {
    "Year": 1977,
    "Month": 1,
    "Day": 12,
    "Hour": 18,
    "Dry-bulb": 14.4,
    "Dew Point": 11.1,
    "RH": 81
  },
  {
    "Year": 1977,
    "Month": 1,
    "Day": 12,
    "Hour": 19,
    "Dry-bulb": 14.4,
    "Dew Point": 11.7,
    "RH": 84
  },
  {
    "Year": 1977,
    "Month": 1,
    "Day": 12,
    "Hour": 20,
    "Dry-bulb": 13.9,
    "Dew Point": 11.1,
    "RH": 83
  },
  {
    "Year": 1977,
    "Month": 1,
    "Day": 12,
    "Hour": 21,
    "Dry-bulb": 13.3,
    "Dew Point": 11.1,
    "RH": 87
  },
  {
    "Year": 1977,
    "Month": 1,
    "Day": 12,
    "Hour": 22,
    "Dry-bulb": 12.2,
    "Dew Point": 10.6,
    "RH": 90
  },
  {
    "Year": 1977,
    "Month": 1,
    "Day": 12,
    "Hour": 23,
    "Dry-bulb": 12.2,
    "Dew Point": 10.6,
    "RH": 90
  },
  {
    "Year": 1977,
    "Month": 1,
    "Day": 12,
    "Hour": 24,
    "Dry-bulb": 12.2,
    "Dew Point": 10.6,
    "RH": 90
  },
  {
    "Year": 1977,
    "Month": 1,
    "Day": 13,
    "Hour": 1,
    "Dry-bulb": 11.7,
    "Dew Point": 10,
    "RH": 90
  },
  {
    "Year": 1977,
    "Month": 1,
    "Day": 13,
    "Hour": 2,
    "Dry-bulb": 11.1,
    "Dew Point": 10,
    "RH": 93
  },
  {
    "Year": 1977,
    "Month": 1,
    "Day": 13,
    "Hour": 3,
    "Dry-bulb": 10,
    "Dew Point": 8.9,
    "RH": 93
  },
  {
    "Year": 1977,
    "Month": 1,
    "Day": 13,
    "Hour": 4,
    "Dry-bulb": 9.4,
    "Dew Point": 8.9,
    "RH": 96
  },
  {
    "Year": 1977,
    "Month": 1,
    "Day": 13,
    "Hour": 5,
    "Dry-bulb": 9.4,
    "Dew Point": 8.3,
    "RH": 93
  },
  {
    "Year": 1977,
    "Month": 1,
    "Day": 13,
    "Hour": 6,
    "Dry-bulb": 9.4,
    "Dew Point": 7.8,
    "RH": 89
  },
  {
    "Year": 1977,
    "Month": 1,
    "Day": 13,
    "Hour": 7,
    "Dry-bulb": 8.3,
    "Dew Point": 7.2,
    "RH": 93
  },
  {
    "Year": 1977,
    "Month": 1,
    "Day": 13,
    "Hour": 8,
    "Dry-bulb": 8.9,
    "Dew Point": 7.2,
    "RH": 89
  },
  {
    "Year": 1977,
    "Month": 1,
    "Day": 13,
    "Hour": 9,
    "Dry-bulb": 11.1,
    "Dew Point": 8.3,
    "RH": 83
  },
  {
    "Year": 1977,
    "Month": 1,
    "Day": 13,
    "Hour": 10,
    "Dry-bulb": 13.9,
    "Dew Point": 8.9,
    "RH": 72
  },
  {
    "Year": 1977,
    "Month": 1,
    "Day": 13,
    "Hour": 11,
    "Dry-bulb": 15.6,
    "Dew Point": 10,
    "RH": 70
  },
  {
    "Year": 1977,
    "Month": 1,
    "Day": 13,
    "Hour": 12,
    "Dry-bulb": 15.6,
    "Dew Point": 10,
    "RH": 70
  },
  {
    "Year": 1977,
    "Month": 1,
    "Day": 13,
    "Hour": 13,
    "Dry-bulb": 16.1,
    "Dew Point": 7.8,
    "RH": 58
  },
  {
    "Year": 1977,
    "Month": 1,
    "Day": 13,
    "Hour": 14,
    "Dry-bulb": 16.7,
    "Dew Point": 11.1,
    "RH": 70
  },
  {
    "Year": 1977,
    "Month": 1,
    "Day": 13,
    "Hour": 15,
    "Dry-bulb": 16.7,
    "Dew Point": 12.2,
    "RH": 75
  },
  {
    "Year": 1977,
    "Month": 1,
    "Day": 13,
    "Hour": 16,
    "Dry-bulb": 16.1,
    "Dew Point": 10.6,
    "RH": 70
  },
  {
    "Year": 1977,
    "Month": 1,
    "Day": 13,
    "Hour": 17,
    "Dry-bulb": 15,
    "Dew Point": 10.6,
    "RH": 75
  },
  {
    "Year": 1977,
    "Month": 1,
    "Day": 13,
    "Hour": 18,
    "Dry-bulb": 13.9,
    "Dew Point": 10,
    "RH": 78
  },
  {
    "Year": 1977,
    "Month": 1,
    "Day": 13,
    "Hour": 19,
    "Dry-bulb": 13.3,
    "Dew Point": 12.2,
    "RH": 93
  },
  {
    "Year": 1977,
    "Month": 1,
    "Day": 13,
    "Hour": 20,
    "Dry-bulb": 13.3,
    "Dew Point": 12.2,
    "RH": 93
  },
  {
    "Year": 1977,
    "Month": 1,
    "Day": 13,
    "Hour": 21,
    "Dry-bulb": 13.3,
    "Dew Point": 10.6,
    "RH": 83
  },
  {
    "Year": 1977,
    "Month": 1,
    "Day": 13,
    "Hour": 22,
    "Dry-bulb": 12.8,
    "Dew Point": 11.1,
    "RH": 90
  },
  {
    "Year": 1977,
    "Month": 1,
    "Day": 13,
    "Hour": 23,
    "Dry-bulb": 12.2,
    "Dew Point": 11.1,
    "RH": 93
  },
  {
    "Year": 1977,
    "Month": 1,
    "Day": 13,
    "Hour": 24,
    "Dry-bulb": 11.1,
    "Dew Point": 10,
    "RH": 93
  },
  {
    "Year": 1977,
    "Month": 1,
    "Day": 14,
    "Hour": 1,
    "Dry-bulb": 10.6,
    "Dew Point": 9.4,
    "RH": 93
  },
  {
    "Year": 1977,
    "Month": 1,
    "Day": 14,
    "Hour": 2,
    "Dry-bulb": 10,
    "Dew Point": 8.9,
    "RH": 93
  },
  {
    "Year": 1977,
    "Month": 1,
    "Day": 14,
    "Hour": 3,
    "Dry-bulb": 10,
    "Dew Point": 8.9,
    "RH": 93
  },
  {
    "Year": 1977,
    "Month": 1,
    "Day": 14,
    "Hour": 4,
    "Dry-bulb": 8.9,
    "Dew Point": 8.3,
    "RH": 96
  },
  {
    "Year": 1977,
    "Month": 1,
    "Day": 14,
    "Hour": 5,
    "Dry-bulb": 9.4,
    "Dew Point": 8.3,
    "RH": 93
  },
  {
    "Year": 1977,
    "Month": 1,
    "Day": 14,
    "Hour": 6,
    "Dry-bulb": 10,
    "Dew Point": 7.8,
    "RH": 86
  },
  {
    "Year": 1977,
    "Month": 1,
    "Day": 14,
    "Hour": 7,
    "Dry-bulb": 10,
    "Dew Point": 7.2,
    "RH": 83
  },
  {
    "Year": 1977,
    "Month": 1,
    "Day": 14,
    "Hour": 8,
    "Dry-bulb": 10,
    "Dew Point": 7.8,
    "RH": 86
  },
  {
    "Year": 1977,
    "Month": 1,
    "Day": 14,
    "Hour": 9,
    "Dry-bulb": 11.1,
    "Dew Point": 8.3,
    "RH": 83
  },
  {
    "Year": 1977,
    "Month": 1,
    "Day": 14,
    "Hour": 10,
    "Dry-bulb": 13.9,
    "Dew Point": 9.4,
    "RH": 75
  },
  {
    "Year": 1977,
    "Month": 1,
    "Day": 14,
    "Hour": 11,
    "Dry-bulb": 16.1,
    "Dew Point": 8.3,
    "RH": 60
  },
  {
    "Year": 1977,
    "Month": 1,
    "Day": 14,
    "Hour": 12,
    "Dry-bulb": 18.3,
    "Dew Point": 6.7,
    "RH": 47
  },
  {
    "Year": 1977,
    "Month": 1,
    "Day": 14,
    "Hour": 13,
    "Dry-bulb": 20,
    "Dew Point": 4.4,
    "RH": 36
  },
  {
    "Year": 1977,
    "Month": 1,
    "Day": 14,
    "Hour": 14,
    "Dry-bulb": 20.6,
    "Dew Point": 5.6,
    "RH": 38
  },
  {
    "Year": 1977,
    "Month": 1,
    "Day": 14,
    "Hour": 15,
    "Dry-bulb": 19.4,
    "Dew Point": 11.7,
    "RH": 61
  },
  {
    "Year": 1977,
    "Month": 1,
    "Day": 14,
    "Hour": 16,
    "Dry-bulb": 17.8,
    "Dew Point": 12.2,
    "RH": 70
  },
  {
    "Year": 1977,
    "Month": 1,
    "Day": 14,
    "Hour": 17,
    "Dry-bulb": 16.1,
    "Dew Point": 12.2,
    "RH": 78
  },
  {
    "Year": 1977,
    "Month": 1,
    "Day": 14,
    "Hour": 18,
    "Dry-bulb": 13.9,
    "Dew Point": 12.2,
    "RH": 90
  },
  {
    "Year": 1977,
    "Month": 1,
    "Day": 14,
    "Hour": 19,
    "Dry-bulb": 13.9,
    "Dew Point": 12.8,
    "RH": 93
  },
  {
    "Year": 1977,
    "Month": 1,
    "Day": 14,
    "Hour": 20,
    "Dry-bulb": 13.9,
    "Dew Point": 12.8,
    "RH": 93
  },
  {
    "Year": 1977,
    "Month": 1,
    "Day": 14,
    "Hour": 21,
    "Dry-bulb": 13.9,
    "Dew Point": 1.7,
    "RH": 44
  },
  {
    "Year": 1977,
    "Month": 1,
    "Day": 14,
    "Hour": 22,
    "Dry-bulb": 13.3,
    "Dew Point": 1.1,
    "RH": 44
  },
  {
    "Year": 1977,
    "Month": 1,
    "Day": 14,
    "Hour": 23,
    "Dry-bulb": 12.2,
    "Dew Point": 5,
    "RH": 62
  },
  {
    "Year": 1977,
    "Month": 1,
    "Day": 14,
    "Hour": 24,
    "Dry-bulb": 11.7,
    "Dew Point": 4.4,
    "RH": 62
  },
  {
    "Year": 1977,
    "Month": 1,
    "Day": 15,
    "Hour": 1,
    "Dry-bulb": 11.7,
    "Dew Point": 2.2,
    "RH": 53
  },
  {
    "Year": 1977,
    "Month": 1,
    "Day": 15,
    "Hour": 2,
    "Dry-bulb": 10,
    "Dew Point": 1.7,
    "RH": 57
  },
  {
    "Year": 1977,
    "Month": 1,
    "Day": 15,
    "Hour": 3,
    "Dry-bulb": 9.4,
    "Dew Point": 1.7,
    "RH": 58
  },
  {
    "Year": 1977,
    "Month": 1,
    "Day": 15,
    "Hour": 4,
    "Dry-bulb": 8.9,
    "Dew Point": 1.7,
    "RH": 61
  },
  {
    "Year": 1977,
    "Month": 1,
    "Day": 15,
    "Hour": 5,
    "Dry-bulb": 9.4,
    "Dew Point": 0.6,
    "RH": 54
  },
  {
    "Year": 1977,
    "Month": 1,
    "Day": 15,
    "Hour": 6,
    "Dry-bulb": 8.3,
    "Dew Point": 1.1,
    "RH": 61
  },
  {
    "Year": 1977,
    "Month": 1,
    "Day": 15,
    "Hour": 7,
    "Dry-bulb": 8.3,
    "Dew Point": 1.1,
    "RH": 61
  },
  {
    "Year": 1977,
    "Month": 1,
    "Day": 15,
    "Hour": 8,
    "Dry-bulb": 9.4,
    "Dew Point": 1.7,
    "RH": 59
  },
  {
    "Year": 1977,
    "Month": 1,
    "Day": 15,
    "Hour": 9,
    "Dry-bulb": 12.2,
    "Dew Point": 2.8,
    "RH": 53
  },
  {
    "Year": 1977,
    "Month": 1,
    "Day": 15,
    "Hour": 10,
    "Dry-bulb": 15.6,
    "Dew Point": 2.8,
    "RH": 43
  },
  {
    "Year": 1977,
    "Month": 1,
    "Day": 15,
    "Hour": 11,
    "Dry-bulb": 17.8,
    "Dew Point": 2.2,
    "RH": 35
  },
  {
    "Year": 1977,
    "Month": 1,
    "Day": 15,
    "Hour": 12,
    "Dry-bulb": 19.4,
    "Dew Point": 1.7,
    "RH": 31
  },
  {
    "Year": 1977,
    "Month": 1,
    "Day": 15,
    "Hour": 13,
    "Dry-bulb": 21.1,
    "Dew Point": 6.1,
    "RH": 38
  },
  {
    "Year": 1977,
    "Month": 1,
    "Day": 15,
    "Hour": 14,
    "Dry-bulb": 20.6,
    "Dew Point": 7.8,
    "RH": 44
  },
  {
    "Year": 1977,
    "Month": 1,
    "Day": 15,
    "Hour": 15,
    "Dry-bulb": 19.4,
    "Dew Point": 7.8,
    "RH": 47
  },
  {
    "Year": 1977,
    "Month": 1,
    "Day": 15,
    "Hour": 16,
    "Dry-bulb": 18.3,
    "Dew Point": 8.3,
    "RH": 52
  },
  {
    "Year": 1977,
    "Month": 1,
    "Day": 15,
    "Hour": 17,
    "Dry-bulb": 17.2,
    "Dew Point": 9.4,
    "RH": 60
  },
  {
    "Year": 1977,
    "Month": 1,
    "Day": 15,
    "Hour": 18,
    "Dry-bulb": 13.9,
    "Dew Point": 12.2,
    "RH": 90
  },
  {
    "Year": 1977,
    "Month": 1,
    "Day": 15,
    "Hour": 19,
    "Dry-bulb": 13.9,
    "Dew Point": 11.7,
    "RH": 87
  },
  {
    "Year": 1977,
    "Month": 1,
    "Day": 15,
    "Hour": 20,
    "Dry-bulb": 13.9,
    "Dew Point": 11.1,
    "RH": 83
  },
  {
    "Year": 1977,
    "Month": 1,
    "Day": 15,
    "Hour": 21,
    "Dry-bulb": 13.9,
    "Dew Point": 11.7,
    "RH": 87
  },
  {
    "Year": 1977,
    "Month": 1,
    "Day": 15,
    "Hour": 22,
    "Dry-bulb": 13.3,
    "Dew Point": 12.2,
    "RH": 93
  },
  {
    "Year": 1977,
    "Month": 1,
    "Day": 15,
    "Hour": 23,
    "Dry-bulb": 12.8,
    "Dew Point": 10.6,
    "RH": 86
  },
  {
    "Year": 1977,
    "Month": 1,
    "Day": 15,
    "Hour": 24,
    "Dry-bulb": 12.2,
    "Dew Point": 8.3,
    "RH": 77
  },
  {
    "Year": 1977,
    "Month": 1,
    "Day": 16,
    "Hour": 1,
    "Dry-bulb": 10.6,
    "Dew Point": 5.6,
    "RH": 71
  },
  {
    "Year": 1977,
    "Month": 1,
    "Day": 16,
    "Hour": 2,
    "Dry-bulb": 10.6,
    "Dew Point": 3.9,
    "RH": 64
  },
  {
    "Year": 1977,
    "Month": 1,
    "Day": 16,
    "Hour": 3,
    "Dry-bulb": 10.6,
    "Dew Point": 2.8,
    "RH": 59
  },
  {
    "Year": 1977,
    "Month": 1,
    "Day": 16,
    "Hour": 4,
    "Dry-bulb": 10,
    "Dew Point": 1.7,
    "RH": 57
  },
  {
    "Year": 1977,
    "Month": 1,
    "Day": 16,
    "Hour": 5,
    "Dry-bulb": 7.8,
    "Dew Point": 2.8,
    "RH": 71
  },
  {
    "Year": 1977,
    "Month": 1,
    "Day": 16,
    "Hour": 6,
    "Dry-bulb": 7.8,
    "Dew Point": 2.8,
    "RH": 71
  },
  {
    "Year": 1977,
    "Month": 1,
    "Day": 16,
    "Hour": 7,
    "Dry-bulb": 7.8,
    "Dew Point": 1.7,
    "RH": 66
  },
  {
    "Year": 1977,
    "Month": 1,
    "Day": 16,
    "Hour": 8,
    "Dry-bulb": 8.9,
    "Dew Point": 2.8,
    "RH": 66
  },
  {
    "Year": 1977,
    "Month": 1,
    "Day": 16,
    "Hour": 9,
    "Dry-bulb": 12.8,
    "Dew Point": 3.3,
    "RH": 53
  },
  {
    "Year": 1977,
    "Month": 1,
    "Day": 16,
    "Hour": 10,
    "Dry-bulb": 16.7,
    "Dew Point": 3.9,
    "RH": 43
  },
  {
    "Year": 1977,
    "Month": 1,
    "Day": 16,
    "Hour": 11,
    "Dry-bulb": 19.4,
    "Dew Point": 2.2,
    "RH": 32
  },
  {
    "Year": 1977,
    "Month": 1,
    "Day": 16,
    "Hour": 12,
    "Dry-bulb": 21.1,
    "Dew Point": 1.7,
    "RH": 28
  },
  {
    "Year": 1977,
    "Month": 1,
    "Day": 16,
    "Hour": 13,
    "Dry-bulb": 23.3,
    "Dew Point": 1.7,
    "RH": 24
  },
  {
    "Year": 1977,
    "Month": 1,
    "Day": 16,
    "Hour": 14,
    "Dry-bulb": 22.2,
    "Dew Point": 7.2,
    "RH": 38
  },
  {
    "Year": 1977,
    "Month": 1,
    "Day": 16,
    "Hour": 15,
    "Dry-bulb": 20.6,
    "Dew Point": 6.1,
    "RH": 39
  },
  {
    "Year": 1977,
    "Month": 1,
    "Day": 16,
    "Hour": 16,
    "Dry-bulb": 19.4,
    "Dew Point": 6.7,
    "RH": 44
  },
  {
    "Year": 1977,
    "Month": 1,
    "Day": 16,
    "Hour": 17,
    "Dry-bulb": 17.2,
    "Dew Point": 6.1,
    "RH": 48
  },
  {
    "Year": 1977,
    "Month": 1,
    "Day": 16,
    "Hour": 18,
    "Dry-bulb": 15,
    "Dew Point": 9.4,
    "RH": 70
  },
  {
    "Year": 1977,
    "Month": 1,
    "Day": 16,
    "Hour": 19,
    "Dry-bulb": 14.4,
    "Dew Point": 11.7,
    "RH": 84
  },
  {
    "Year": 1977,
    "Month": 1,
    "Day": 16,
    "Hour": 20,
    "Dry-bulb": 14.4,
    "Dew Point": 11.1,
    "RH": 81
  },
  {
    "Year": 1977,
    "Month": 1,
    "Day": 16,
    "Hour": 21,
    "Dry-bulb": 14.4,
    "Dew Point": 7.8,
    "RH": 65
  },
  {
    "Year": 1977,
    "Month": 1,
    "Day": 16,
    "Hour": 22,
    "Dry-bulb": 12.2,
    "Dew Point": 6.7,
    "RH": 69
  },
  {
    "Year": 1977,
    "Month": 1,
    "Day": 16,
    "Hour": 23,
    "Dry-bulb": 13.3,
    "Dew Point": 3.9,
    "RH": 53
  },
  {
    "Year": 1977,
    "Month": 1,
    "Day": 16,
    "Hour": 24,
    "Dry-bulb": 12.2,
    "Dew Point": 3.3,
    "RH": 55
  },
  {
    "Year": 1977,
    "Month": 1,
    "Day": 17,
    "Hour": 1,
    "Dry-bulb": 11.7,
    "Dew Point": 2.2,
    "RH": 53
  },
  {
    "Year": 1977,
    "Month": 1,
    "Day": 17,
    "Hour": 2,
    "Dry-bulb": 9.4,
    "Dew Point": 2.2,
    "RH": 61
  },
  {
    "Year": 1977,
    "Month": 1,
    "Day": 17,
    "Hour": 3,
    "Dry-bulb": 10.6,
    "Dew Point": 0,
    "RH": 48
  },
  {
    "Year": 1977,
    "Month": 1,
    "Day": 17,
    "Hour": 4,
    "Dry-bulb": 11.7,
    "Dew Point": -2.2,
    "RH": 38
  },
  {
    "Year": 1977,
    "Month": 1,
    "Day": 17,
    "Hour": 5,
    "Dry-bulb": 13.3,
    "Dew Point": -2.8,
    "RH": 33
  },
  {
    "Year": 1977,
    "Month": 1,
    "Day": 17,
    "Hour": 6,
    "Dry-bulb": 11.7,
    "Dew Point": -2.2,
    "RH": 38
  },
  {
    "Year": 1977,
    "Month": 1,
    "Day": 17,
    "Hour": 7,
    "Dry-bulb": 12.8,
    "Dew Point": -3.3,
    "RH": 33
  },
  {
    "Year": 1977,
    "Month": 1,
    "Day": 17,
    "Hour": 8,
    "Dry-bulb": 12.8,
    "Dew Point": -0.6,
    "RH": 40
  },
  {
    "Year": 1977,
    "Month": 1,
    "Day": 17,
    "Hour": 9,
    "Dry-bulb": 18.3,
    "Dew Point": -0.6,
    "RH": 28
  },
  {
    "Year": 1977,
    "Month": 1,
    "Day": 17,
    "Hour": 10,
    "Dry-bulb": 21.1,
    "Dew Point": 1.7,
    "RH": 28
  },
  {
    "Year": 1977,
    "Month": 1,
    "Day": 17,
    "Hour": 11,
    "Dry-bulb": 23.9,
    "Dew Point": 1.7,
    "RH": 23
  },
  {
    "Year": 1977,
    "Month": 1,
    "Day": 17,
    "Hour": 12,
    "Dry-bulb": 25,
    "Dew Point": -1.1,
    "RH": 18
  },
  {
    "Year": 1977,
    "Month": 1,
    "Day": 17,
    "Hour": 13,
    "Dry-bulb": 26.1,
    "Dew Point": -1.7,
    "RH": 16
  },
  {
    "Year": 1977,
    "Month": 1,
    "Day": 17,
    "Hour": 14,
    "Dry-bulb": 27.2,
    "Dew Point": 0,
    "RH": 17
  },
  {
    "Year": 1977,
    "Month": 1,
    "Day": 17,
    "Hour": 15,
    "Dry-bulb": 26.7,
    "Dew Point": 2.2,
    "RH": 21
  },
  {
    "Year": 1977,
    "Month": 1,
    "Day": 17,
    "Hour": 16,
    "Dry-bulb": 23.9,
    "Dew Point": 5.6,
    "RH": 31
  },
  {
    "Year": 1977,
    "Month": 1,
    "Day": 17,
    "Hour": 17,
    "Dry-bulb": 22.2,
    "Dew Point": 1.1,
    "RH": 25
  },
  {
    "Year": 1977,
    "Month": 1,
    "Day": 17,
    "Hour": 18,
    "Dry-bulb": 21.7,
    "Dew Point": 1.7,
    "RH": 27
  },
  {
    "Year": 1977,
    "Month": 1,
    "Day": 17,
    "Hour": 19,
    "Dry-bulb": 21.1,
    "Dew Point": -3.9,
    "RH": 18
  },
  {
    "Year": 1977,
    "Month": 1,
    "Day": 17,
    "Hour": 20,
    "Dry-bulb": 21.1,
    "Dew Point": -3.9,
    "RH": 18
  },
  {
    "Year": 1977,
    "Month": 1,
    "Day": 17,
    "Hour": 21,
    "Dry-bulb": 20.6,
    "Dew Point": -3.9,
    "RH": 19
  },
  {
    "Year": 1977,
    "Month": 1,
    "Day": 17,
    "Hour": 22,
    "Dry-bulb": 18.3,
    "Dew Point": -2.8,
    "RH": 24
  },
  {
    "Year": 1977,
    "Month": 1,
    "Day": 17,
    "Hour": 23,
    "Dry-bulb": 15,
    "Dew Point": 2.8,
    "RH": 44
  },
  {
    "Year": 1977,
    "Month": 1,
    "Day": 17,
    "Hour": 24,
    "Dry-bulb": 15,
    "Dew Point": 1.7,
    "RH": 41
  },
  {
    "Year": 1977,
    "Month": 1,
    "Day": 18,
    "Hour": 1,
    "Dry-bulb": 15,
    "Dew Point": 0.6,
    "RH": 38
  },
  {
    "Year": 1977,
    "Month": 1,
    "Day": 18,
    "Hour": 2,
    "Dry-bulb": 13.9,
    "Dew Point": 2.2,
    "RH": 46
  },
  {
    "Year": 1977,
    "Month": 1,
    "Day": 18,
    "Hour": 3,
    "Dry-bulb": 13.3,
    "Dew Point": 1.7,
    "RH": 45
  },
  {
    "Year": 1977,
    "Month": 1,
    "Day": 18,
    "Hour": 4,
    "Dry-bulb": 12.8,
    "Dew Point": 2.2,
    "RH": 49
  },
  {
    "Year": 1977,
    "Month": 1,
    "Day": 18,
    "Hour": 5,
    "Dry-bulb": 13.3,
    "Dew Point": 1.1,
    "RH": 44
  },
  {
    "Year": 1977,
    "Month": 1,
    "Day": 18,
    "Hour": 6,
    "Dry-bulb": 13.3,
    "Dew Point": 0,
    "RH": 40
  },
  {
    "Year": 1977,
    "Month": 1,
    "Day": 18,
    "Hour": 7,
    "Dry-bulb": 13.3,
    "Dew Point": 0,
    "RH": 40
  },
  {
    "Year": 1977,
    "Month": 1,
    "Day": 18,
    "Hour": 8,
    "Dry-bulb": 16.1,
    "Dew Point": 0.6,
    "RH": 35
  },
  {
    "Year": 1977,
    "Month": 1,
    "Day": 18,
    "Hour": 9,
    "Dry-bulb": 17.8,
    "Dew Point": 3.3,
    "RH": 38
  },
  {
    "Year": 1977,
    "Month": 1,
    "Day": 18,
    "Hour": 10,
    "Dry-bulb": 20,
    "Dew Point": 5.6,
    "RH": 39
  },
  {
    "Year": 1977,
    "Month": 1,
    "Day": 18,
    "Hour": 11,
    "Dry-bulb": 22.8,
    "Dew Point": 3.9,
    "RH": 29
  },
  {
    "Year": 1977,
    "Month": 1,
    "Day": 18,
    "Hour": 12,
    "Dry-bulb": 25,
    "Dew Point": 6.1,
    "RH": 30
  },
  {
    "Year": 1977,
    "Month": 1,
    "Day": 18,
    "Hour": 13,
    "Dry-bulb": 26.1,
    "Dew Point": 5.6,
    "RH": 27
  },
  {
    "Year": 1977,
    "Month": 1,
    "Day": 18,
    "Hour": 14,
    "Dry-bulb": 24.4,
    "Dew Point": 7.2,
    "RH": 33
  },
  {
    "Year": 1977,
    "Month": 1,
    "Day": 18,
    "Hour": 15,
    "Dry-bulb": 24.4,
    "Dew Point": 5.6,
    "RH": 30
  },
  {
    "Year": 1977,
    "Month": 1,
    "Day": 18,
    "Hour": 16,
    "Dry-bulb": 21.7,
    "Dew Point": 10,
    "RH": 48
  },
  {
    "Year": 1977,
    "Month": 1,
    "Day": 18,
    "Hour": 17,
    "Dry-bulb": 19.4,
    "Dew Point": 7.2,
    "RH": 45
  },
  {
    "Year": 1977,
    "Month": 1,
    "Day": 18,
    "Hour": 18,
    "Dry-bulb": 17.2,
    "Dew Point": 8.3,
    "RH": 56
  },
  {
    "Year": 1977,
    "Month": 1,
    "Day": 18,
    "Hour": 19,
    "Dry-bulb": 17.2,
    "Dew Point": 8.3,
    "RH": 56
  },
  {
    "Year": 1977,
    "Month": 1,
    "Day": 18,
    "Hour": 20,
    "Dry-bulb": 17.2,
    "Dew Point": 7.2,
    "RH": 52
  },
  {
    "Year": 1977,
    "Month": 1,
    "Day": 18,
    "Hour": 21,
    "Dry-bulb": 17.2,
    "Dew Point": 7.8,
    "RH": 54
  },
  {
    "Year": 1977,
    "Month": 1,
    "Day": 18,
    "Hour": 22,
    "Dry-bulb": 17.2,
    "Dew Point": 6.1,
    "RH": 48
  },
  {
    "Year": 1977,
    "Month": 1,
    "Day": 18,
    "Hour": 23,
    "Dry-bulb": 17.2,
    "Dew Point": 6.1,
    "RH": 48
  },
  {
    "Year": 1977,
    "Month": 1,
    "Day": 18,
    "Hour": 24,
    "Dry-bulb": 16.7,
    "Dew Point": 6.1,
    "RH": 50
  },
  {
    "Year": 1977,
    "Month": 1,
    "Day": 19,
    "Hour": 1,
    "Dry-bulb": 15.6,
    "Dew Point": 5.6,
    "RH": 52
  },
  {
    "Year": 1977,
    "Month": 1,
    "Day": 19,
    "Hour": 2,
    "Dry-bulb": 15.6,
    "Dew Point": 5.6,
    "RH": 52
  },
  {
    "Year": 1977,
    "Month": 1,
    "Day": 19,
    "Hour": 3,
    "Dry-bulb": 15,
    "Dew Point": 5,
    "RH": 51
  },
  {
    "Year": 1977,
    "Month": 1,
    "Day": 19,
    "Hour": 4,
    "Dry-bulb": 13.3,
    "Dew Point": 6.1,
    "RH": 62
  },
  {
    "Year": 1977,
    "Month": 1,
    "Day": 19,
    "Hour": 5,
    "Dry-bulb": 13.3,
    "Dew Point": 5,
    "RH": 57
  },
  {
    "Year": 1977,
    "Month": 1,
    "Day": 19,
    "Hour": 6,
    "Dry-bulb": 13.3,
    "Dew Point": 5,
    "RH": 57
  },
  {
    "Year": 1977,
    "Month": 1,
    "Day": 19,
    "Hour": 7,
    "Dry-bulb": 13.3,
    "Dew Point": 4.4,
    "RH": 55
  },
  {
    "Year": 1977,
    "Month": 1,
    "Day": 19,
    "Hour": 8,
    "Dry-bulb": 15,
    "Dew Point": 4.4,
    "RH": 50
  },
  {
    "Year": 1977,
    "Month": 1,
    "Day": 19,
    "Hour": 9,
    "Dry-bulb": 16.1,
    "Dew Point": 5,
    "RH": 48
  },
  {
    "Year": 1977,
    "Month": 1,
    "Day": 19,
    "Hour": 10,
    "Dry-bulb": 16.7,
    "Dew Point": 7.2,
    "RH": 54
  },
  {
    "Year": 1977,
    "Month": 1,
    "Day": 19,
    "Hour": 11,
    "Dry-bulb": 18.3,
    "Dew Point": 7.8,
    "RH": 50
  },
  {
    "Year": 1977,
    "Month": 1,
    "Day": 19,
    "Hour": 12,
    "Dry-bulb": 21.1,
    "Dew Point": 7.8,
    "RH": 42
  },
  {
    "Year": 1977,
    "Month": 1,
    "Day": 19,
    "Hour": 13,
    "Dry-bulb": 22.2,
    "Dew Point": 7.2,
    "RH": 38
  },
  {
    "Year": 1977,
    "Month": 1,
    "Day": 19,
    "Hour": 14,
    "Dry-bulb": 23.3,
    "Dew Point": 6.7,
    "RH": 34
  },
  {
    "Year": 1977,
    "Month": 1,
    "Day": 19,
    "Hour": 15,
    "Dry-bulb": 21.7,
    "Dew Point": 13.9,
    "RH": 61
  },
  {
    "Year": 1977,
    "Month": 1,
    "Day": 19,
    "Hour": 16,
    "Dry-bulb": 18.9,
    "Dew Point": 13.3,
    "RH": 70
  },
  {
    "Year": 1977,
    "Month": 1,
    "Day": 19,
    "Hour": 17,
    "Dry-bulb": 17.2,
    "Dew Point": 11.1,
    "RH": 68
  },
  {
    "Year": 1977,
    "Month": 1,
    "Day": 19,
    "Hour": 18,
    "Dry-bulb": 16.7,
    "Dew Point": 11.1,
    "RH": 70
  },
  {
    "Year": 1977,
    "Month": 1,
    "Day": 19,
    "Hour": 19,
    "Dry-bulb": 16.7,
    "Dew Point": 12.2,
    "RH": 75
  },
  {
    "Year": 1977,
    "Month": 1,
    "Day": 19,
    "Hour": 20,
    "Dry-bulb": 16.1,
    "Dew Point": 12.2,
    "RH": 78
  },
  {
    "Year": 1977,
    "Month": 1,
    "Day": 19,
    "Hour": 21,
    "Dry-bulb": 16.1,
    "Dew Point": 12.8,
    "RH": 81
  },
  {
    "Year": 1977,
    "Month": 1,
    "Day": 19,
    "Hour": 22,
    "Dry-bulb": 16.1,
    "Dew Point": 12.8,
    "RH": 81
  },
  {
    "Year": 1977,
    "Month": 1,
    "Day": 19,
    "Hour": 23,
    "Dry-bulb": 15.6,
    "Dew Point": 11.1,
    "RH": 75
  },
  {
    "Year": 1977,
    "Month": 1,
    "Day": 19,
    "Hour": 24,
    "Dry-bulb": 14.4,
    "Dew Point": 11.1,
    "RH": 81
  },
  {
    "Year": 1977,
    "Month": 1,
    "Day": 20,
    "Hour": 1,
    "Dry-bulb": 14.4,
    "Dew Point": 11.7,
    "RH": 84
  },
  {
    "Year": 1977,
    "Month": 1,
    "Day": 20,
    "Hour": 2,
    "Dry-bulb": 13.9,
    "Dew Point": 11.7,
    "RH": 87
  },
  {
    "Year": 1977,
    "Month": 1,
    "Day": 20,
    "Hour": 3,
    "Dry-bulb": 13.9,
    "Dew Point": 11.7,
    "RH": 87
  },
  {
    "Year": 1977,
    "Month": 1,
    "Day": 20,
    "Hour": 4,
    "Dry-bulb": 13.9,
    "Dew Point": 11.1,
    "RH": 83
  },
  {
    "Year": 1977,
    "Month": 1,
    "Day": 20,
    "Hour": 5,
    "Dry-bulb": 13.9,
    "Dew Point": 8.9,
    "RH": 72
  },
  {
    "Year": 1977,
    "Month": 1,
    "Day": 20,
    "Hour": 6,
    "Dry-bulb": 13.9,
    "Dew Point": 9.4,
    "RH": 75
  },
  {
    "Year": 1977,
    "Month": 1,
    "Day": 20,
    "Hour": 7,
    "Dry-bulb": 14.4,
    "Dew Point": 8.9,
    "RH": 70
  },
  {
    "Year": 1977,
    "Month": 1,
    "Day": 20,
    "Hour": 8,
    "Dry-bulb": 14.4,
    "Dew Point": 8.9,
    "RH": 70
  },
  {
    "Year": 1977,
    "Month": 1,
    "Day": 20,
    "Hour": 9,
    "Dry-bulb": 15.6,
    "Dew Point": 9.4,
    "RH": 67
  },
  {
    "Year": 1977,
    "Month": 1,
    "Day": 20,
    "Hour": 10,
    "Dry-bulb": 16.1,
    "Dew Point": 10,
    "RH": 67
  },
  {
    "Year": 1977,
    "Month": 1,
    "Day": 20,
    "Hour": 11,
    "Dry-bulb": 17.2,
    "Dew Point": 13.9,
    "RH": 81
  },
  {
    "Year": 1977,
    "Month": 1,
    "Day": 20,
    "Hour": 12,
    "Dry-bulb": 18.3,
    "Dew Point": 10,
    "RH": 59
  },
  {
    "Year": 1977,
    "Month": 1,
    "Day": 20,
    "Hour": 13,
    "Dry-bulb": 18.9,
    "Dew Point": 9.4,
    "RH": 54
  },
  {
    "Year": 1977,
    "Month": 1,
    "Day": 20,
    "Hour": 14,
    "Dry-bulb": 19.4,
    "Dew Point": 7.8,
    "RH": 47
  },
  {
    "Year": 1977,
    "Month": 1,
    "Day": 20,
    "Hour": 15,
    "Dry-bulb": 18.3,
    "Dew Point": 12.8,
    "RH": 70
  },
  {
    "Year": 1977,
    "Month": 1,
    "Day": 20,
    "Hour": 16,
    "Dry-bulb": 16.7,
    "Dew Point": 11.1,
    "RH": 70
  },
  {
    "Year": 1977,
    "Month": 1,
    "Day": 20,
    "Hour": 17,
    "Dry-bulb": 16.1,
    "Dew Point": 12.8,
    "RH": 81
  },
  {
    "Year": 1977,
    "Month": 1,
    "Day": 20,
    "Hour": 18,
    "Dry-bulb": 15.6,
    "Dew Point": 11.7,
    "RH": 78
  },
  {
    "Year": 1977,
    "Month": 1,
    "Day": 20,
    "Hour": 19,
    "Dry-bulb": 15.6,
    "Dew Point": 12.8,
    "RH": 84
  },
  {
    "Year": 1977,
    "Month": 1,
    "Day": 20,
    "Hour": 20,
    "Dry-bulb": 15.6,
    "Dew Point": 13.3,
    "RH": 87
  },
  {
    "Year": 1977,
    "Month": 1,
    "Day": 20,
    "Hour": 21,
    "Dry-bulb": 15,
    "Dew Point": 12.2,
    "RH": 84
  },
  {
    "Year": 1977,
    "Month": 1,
    "Day": 20,
    "Hour": 22,
    "Dry-bulb": 14.4,
    "Dew Point": 12.2,
    "RH": 87
  },
  {
    "Year": 1977,
    "Month": 1,
    "Day": 20,
    "Hour": 23,
    "Dry-bulb": 14.4,
    "Dew Point": 12.8,
    "RH": 90
  },
  {
    "Year": 1977,
    "Month": 1,
    "Day": 20,
    "Hour": 24,
    "Dry-bulb": 14.4,
    "Dew Point": 13.3,
    "RH": 93
  },
  {
    "Year": 1977,
    "Month": 1,
    "Day": 21,
    "Hour": 1,
    "Dry-bulb": 14.4,
    "Dew Point": 13.3,
    "RH": 93
  },
  {
    "Year": 1977,
    "Month": 1,
    "Day": 21,
    "Hour": 2,
    "Dry-bulb": 14.4,
    "Dew Point": 13.9,
    "RH": 96
  },
  {
    "Year": 1977,
    "Month": 1,
    "Day": 21,
    "Hour": 3,
    "Dry-bulb": 14.4,
    "Dew Point": 13.3,
    "RH": 93
  },
  {
    "Year": 1977,
    "Month": 1,
    "Day": 21,
    "Hour": 4,
    "Dry-bulb": 13.9,
    "Dew Point": 13.3,
    "RH": 96
  },
  {
    "Year": 1977,
    "Month": 1,
    "Day": 21,
    "Hour": 5,
    "Dry-bulb": 13.9,
    "Dew Point": 13.3,
    "RH": 96
  },
  {
    "Year": 1977,
    "Month": 1,
    "Day": 21,
    "Hour": 6,
    "Dry-bulb": 13.9,
    "Dew Point": 13.3,
    "RH": 96
  },
  {
    "Year": 1977,
    "Month": 1,
    "Day": 21,
    "Hour": 7,
    "Dry-bulb": 13.9,
    "Dew Point": 13.3,
    "RH": 96
  },
  {
    "Year": 1977,
    "Month": 1,
    "Day": 21,
    "Hour": 8,
    "Dry-bulb": 13.9,
    "Dew Point": 13.3,
    "RH": 96
  },
  {
    "Year": 1977,
    "Month": 1,
    "Day": 21,
    "Hour": 9,
    "Dry-bulb": 13.9,
    "Dew Point": 12.8,
    "RH": 93
  },
  {
    "Year": 1977,
    "Month": 1,
    "Day": 21,
    "Hour": 10,
    "Dry-bulb": 15,
    "Dew Point": 13.3,
    "RH": 90
  },
  {
    "Year": 1977,
    "Month": 1,
    "Day": 21,
    "Hour": 11,
    "Dry-bulb": 15.6,
    "Dew Point": 13.3,
    "RH": 87
  },
  {
    "Year": 1977,
    "Month": 1,
    "Day": 21,
    "Hour": 12,
    "Dry-bulb": 16.1,
    "Dew Point": 13.9,
    "RH": 87
  },
  {
    "Year": 1977,
    "Month": 1,
    "Day": 21,
    "Hour": 13,
    "Dry-bulb": 17.2,
    "Dew Point": 14.4,
    "RH": 84
  },
  {
    "Year": 1977,
    "Month": 1,
    "Day": 21,
    "Hour": 14,
    "Dry-bulb": 17.8,
    "Dew Point": 13.9,
    "RH": 78
  },
  {
    "Year": 1977,
    "Month": 1,
    "Day": 21,
    "Hour": 15,
    "Dry-bulb": 17.2,
    "Dew Point": 13.3,
    "RH": 78
  },
  {
    "Year": 1977,
    "Month": 1,
    "Day": 21,
    "Hour": 16,
    "Dry-bulb": 16.7,
    "Dew Point": 13.3,
    "RH": 81
  },
  {
    "Year": 1977,
    "Month": 1,
    "Day": 21,
    "Hour": 17,
    "Dry-bulb": 15.6,
    "Dew Point": 12.8,
    "RH": 84
  },
  {
    "Year": 1977,
    "Month": 1,
    "Day": 21,
    "Hour": 18,
    "Dry-bulb": 14.4,
    "Dew Point": 12.2,
    "RH": 87
  },
  {
    "Year": 1977,
    "Month": 1,
    "Day": 21,
    "Hour": 19,
    "Dry-bulb": 14.4,
    "Dew Point": 12.8,
    "RH": 90
  },
  {
    "Year": 1977,
    "Month": 1,
    "Day": 21,
    "Hour": 20,
    "Dry-bulb": 14.4,
    "Dew Point": 12.8,
    "RH": 90
  },
  {
    "Year": 1977,
    "Month": 1,
    "Day": 21,
    "Hour": 21,
    "Dry-bulb": 14.4,
    "Dew Point": 12.8,
    "RH": 90
  },
  {
    "Year": 1977,
    "Month": 1,
    "Day": 21,
    "Hour": 22,
    "Dry-bulb": 14.4,
    "Dew Point": 12.8,
    "RH": 90
  },
  {
    "Year": 1977,
    "Month": 1,
    "Day": 21,
    "Hour": 23,
    "Dry-bulb": 13.9,
    "Dew Point": 12.8,
    "RH": 93
  },
  {
    "Year": 1977,
    "Month": 1,
    "Day": 21,
    "Hour": 24,
    "Dry-bulb": 13.9,
    "Dew Point": 12.2,
    "RH": 90
  },
  {
    "Year": 1977,
    "Month": 1,
    "Day": 22,
    "Hour": 1,
    "Dry-bulb": 13.9,
    "Dew Point": 11.7,
    "RH": 87
  },
  {
    "Year": 1977,
    "Month": 1,
    "Day": 22,
    "Hour": 2,
    "Dry-bulb": 13.3,
    "Dew Point": 11.7,
    "RH": 90
  },
  {
    "Year": 1977,
    "Month": 1,
    "Day": 22,
    "Hour": 3,
    "Dry-bulb": 12.2,
    "Dew Point": 11.1,
    "RH": 93
  },
  {
    "Year": 1977,
    "Month": 1,
    "Day": 22,
    "Hour": 4,
    "Dry-bulb": 12.2,
    "Dew Point": 11.1,
    "RH": 93
  },
  {
    "Year": 1977,
    "Month": 1,
    "Day": 22,
    "Hour": 5,
    "Dry-bulb": 12.2,
    "Dew Point": 11.1,
    "RH": 93
  },
  {
    "Year": 1977,
    "Month": 1,
    "Day": 22,
    "Hour": 6,
    "Dry-bulb": 12.2,
    "Dew Point": 11.1,
    "RH": 93
  },
  {
    "Year": 1977,
    "Month": 1,
    "Day": 22,
    "Hour": 7,
    "Dry-bulb": 12.2,
    "Dew Point": 11.1,
    "RH": 93
  },
  {
    "Year": 1977,
    "Month": 1,
    "Day": 22,
    "Hour": 8,
    "Dry-bulb": 12.2,
    "Dew Point": 11.1,
    "RH": 93
  },
  {
    "Year": 1977,
    "Month": 1,
    "Day": 22,
    "Hour": 9,
    "Dry-bulb": 13.3,
    "Dew Point": 12.8,
    "RH": 96
  },
  {
    "Year": 1977,
    "Month": 1,
    "Day": 22,
    "Hour": 10,
    "Dry-bulb": 15,
    "Dew Point": 13.3,
    "RH": 90
  },
  {
    "Year": 1977,
    "Month": 1,
    "Day": 22,
    "Hour": 11,
    "Dry-bulb": 16.7,
    "Dew Point": 13.9,
    "RH": 84
  },
  {
    "Year": 1977,
    "Month": 1,
    "Day": 22,
    "Hour": 12,
    "Dry-bulb": 17.2,
    "Dew Point": 13.9,
    "RH": 81
  },
  {
    "Year": 1977,
    "Month": 1,
    "Day": 22,
    "Hour": 13,
    "Dry-bulb": 17.8,
    "Dew Point": 13.3,
    "RH": 75
  },
  {
    "Year": 1977,
    "Month": 1,
    "Day": 22,
    "Hour": 14,
    "Dry-bulb": 17.8,
    "Dew Point": 13.3,
    "RH": 75
  },
  {
    "Year": 1977,
    "Month": 1,
    "Day": 22,
    "Hour": 15,
    "Dry-bulb": 17.8,
    "Dew Point": 12.8,
    "RH": 73
  },
  {
    "Year": 1977,
    "Month": 1,
    "Day": 22,
    "Hour": 16,
    "Dry-bulb": 17.2,
    "Dew Point": 11.1,
    "RH": 68
  },
  {
    "Year": 1977,
    "Month": 1,
    "Day": 22,
    "Hour": 17,
    "Dry-bulb": 16.7,
    "Dew Point": 13.3,
    "RH": 81
  },
  {
    "Year": 1977,
    "Month": 1,
    "Day": 22,
    "Hour": 18,
    "Dry-bulb": 15.6,
    "Dew Point": 13.3,
    "RH": 87
  },
  {
    "Year": 1977,
    "Month": 1,
    "Day": 22,
    "Hour": 19,
    "Dry-bulb": 15,
    "Dew Point": 13.3,
    "RH": 90
  },
  {
    "Year": 1977,
    "Month": 1,
    "Day": 22,
    "Hour": 20,
    "Dry-bulb": 14.4,
    "Dew Point": 13.3,
    "RH": 93
  },
  {
    "Year": 1977,
    "Month": 1,
    "Day": 22,
    "Hour": 21,
    "Dry-bulb": 14.4,
    "Dew Point": 13.3,
    "RH": 93
  },
  {
    "Year": 1977,
    "Month": 1,
    "Day": 22,
    "Hour": 22,
    "Dry-bulb": 13.9,
    "Dew Point": 12.8,
    "RH": 93
  },
  {
    "Year": 1977,
    "Month": 1,
    "Day": 22,
    "Hour": 23,
    "Dry-bulb": 13.3,
    "Dew Point": 12.2,
    "RH": 93
  },
  {
    "Year": 1977,
    "Month": 1,
    "Day": 22,
    "Hour": 24,
    "Dry-bulb": 13.3,
    "Dew Point": 12.2,
    "RH": 93
  },
  {
    "Year": 1977,
    "Month": 1,
    "Day": 23,
    "Hour": 1,
    "Dry-bulb": 13.3,
    "Dew Point": 12.2,
    "RH": 93
  },
  {
    "Year": 1977,
    "Month": 1,
    "Day": 23,
    "Hour": 2,
    "Dry-bulb": 12.8,
    "Dew Point": 11.1,
    "RH": 90
  },
  {
    "Year": 1977,
    "Month": 1,
    "Day": 23,
    "Hour": 3,
    "Dry-bulb": 12.8,
    "Dew Point": 11.1,
    "RH": 90
  },
  {
    "Year": 1977,
    "Month": 1,
    "Day": 23,
    "Hour": 4,
    "Dry-bulb": 11.1,
    "Dew Point": 10,
    "RH": 93
  },
  {
    "Year": 1977,
    "Month": 1,
    "Day": 23,
    "Hour": 5,
    "Dry-bulb": 11.1,
    "Dew Point": 9.4,
    "RH": 90
  },
  {
    "Year": 1977,
    "Month": 1,
    "Day": 23,
    "Hour": 6,
    "Dry-bulb": 11.1,
    "Dew Point": 9.4,
    "RH": 90
  },
  {
    "Year": 1977,
    "Month": 1,
    "Day": 23,
    "Hour": 7,
    "Dry-bulb": 11.1,
    "Dew Point": 9.4,
    "RH": 90
  },
  {
    "Year": 1977,
    "Month": 1,
    "Day": 23,
    "Hour": 8,
    "Dry-bulb": 10.6,
    "Dew Point": 10,
    "RH": 96
  },
  {
    "Year": 1977,
    "Month": 1,
    "Day": 23,
    "Hour": 9,
    "Dry-bulb": 12.8,
    "Dew Point": 10.6,
    "RH": 86
  },
  {
    "Year": 1977,
    "Month": 1,
    "Day": 23,
    "Hour": 10,
    "Dry-bulb": 15,
    "Dew Point": 11.1,
    "RH": 78
  },
  {
    "Year": 1977,
    "Month": 1,
    "Day": 23,
    "Hour": 11,
    "Dry-bulb": 16.7,
    "Dew Point": 11.1,
    "RH": 70
  },
  {
    "Year": 1977,
    "Month": 1,
    "Day": 23,
    "Hour": 12,
    "Dry-bulb": 17.8,
    "Dew Point": 13.3,
    "RH": 75
  },
  {
    "Year": 1977,
    "Month": 1,
    "Day": 23,
    "Hour": 13,
    "Dry-bulb": 17.8,
    "Dew Point": 13.9,
    "RH": 78
  },
  {
    "Year": 1977,
    "Month": 1,
    "Day": 23,
    "Hour": 14,
    "Dry-bulb": 17.8,
    "Dew Point": 12.8,
    "RH": 73
  },
  {
    "Year": 1977,
    "Month": 1,
    "Day": 23,
    "Hour": 15,
    "Dry-bulb": 17.8,
    "Dew Point": 13.3,
    "RH": 75
  },
  {
    "Year": 1977,
    "Month": 1,
    "Day": 23,
    "Hour": 16,
    "Dry-bulb": 17.8,
    "Dew Point": 13.9,
    "RH": 78
  },
  {
    "Year": 1977,
    "Month": 1,
    "Day": 23,
    "Hour": 17,
    "Dry-bulb": 16.7,
    "Dew Point": 13.9,
    "RH": 84
  },
  {
    "Year": 1977,
    "Month": 1,
    "Day": 23,
    "Hour": 18,
    "Dry-bulb": 15,
    "Dew Point": 13.3,
    "RH": 90
  },
  {
    "Year": 1977,
    "Month": 1,
    "Day": 23,
    "Hour": 19,
    "Dry-bulb": 15,
    "Dew Point": 13.9,
    "RH": 93
  },
  {
    "Year": 1977,
    "Month": 1,
    "Day": 23,
    "Hour": 20,
    "Dry-bulb": 15,
    "Dew Point": 13.3,
    "RH": 90
  },
  {
    "Year": 1977,
    "Month": 1,
    "Day": 23,
    "Hour": 21,
    "Dry-bulb": 13.9,
    "Dew Point": 12.8,
    "RH": 93
  },
  {
    "Year": 1977,
    "Month": 1,
    "Day": 23,
    "Hour": 22,
    "Dry-bulb": 13.9,
    "Dew Point": 12.8,
    "RH": 93
  },
  {
    "Year": 1977,
    "Month": 1,
    "Day": 23,
    "Hour": 23,
    "Dry-bulb": 13.3,
    "Dew Point": 12.2,
    "RH": 93
  },
  {
    "Year": 1977,
    "Month": 1,
    "Day": 23,
    "Hour": 24,
    "Dry-bulb": 13.3,
    "Dew Point": 11.7,
    "RH": 90
  },
  {
    "Year": 1977,
    "Month": 1,
    "Day": 24,
    "Hour": 1,
    "Dry-bulb": 12.8,
    "Dew Point": 10,
    "RH": 83
  },
  {
    "Year": 1977,
    "Month": 1,
    "Day": 24,
    "Hour": 2,
    "Dry-bulb": 11.7,
    "Dew Point": 8.3,
    "RH": 80
  },
  {
    "Year": 1977,
    "Month": 1,
    "Day": 24,
    "Hour": 3,
    "Dry-bulb": 11.1,
    "Dew Point": 7.8,
    "RH": 80
  },
  {
    "Year": 1977,
    "Month": 1,
    "Day": 24,
    "Hour": 4,
    "Dry-bulb": 11.1,
    "Dew Point": 7.2,
    "RH": 77
  },
  {
    "Year": 1977,
    "Month": 1,
    "Day": 24,
    "Hour": 5,
    "Dry-bulb": 10,
    "Dew Point": 6.1,
    "RH": 77
  },
  {
    "Year": 1977,
    "Month": 1,
    "Day": 24,
    "Hour": 6,
    "Dry-bulb": 10,
    "Dew Point": 6.1,
    "RH": 77
  },
  {
    "Year": 1977,
    "Month": 1,
    "Day": 24,
    "Hour": 7,
    "Dry-bulb": 9.4,
    "Dew Point": 6.7,
    "RH": 83
  },
  {
    "Year": 1977,
    "Month": 1,
    "Day": 24,
    "Hour": 8,
    "Dry-bulb": 11.7,
    "Dew Point": 7.8,
    "RH": 77
  },
  {
    "Year": 1977,
    "Month": 1,
    "Day": 24,
    "Hour": 9,
    "Dry-bulb": 15.6,
    "Dew Point": 7.8,
    "RH": 60
  },
  {
    "Year": 1977,
    "Month": 1,
    "Day": 24,
    "Hour": 10,
    "Dry-bulb": 17.8,
    "Dew Point": 7.8,
    "RH": 52
  },
  {
    "Year": 1977,
    "Month": 1,
    "Day": 24,
    "Hour": 11,
    "Dry-bulb": 20,
    "Dew Point": 7.8,
    "RH": 45
  },
  {
    "Year": 1977,
    "Month": 1,
    "Day": 24,
    "Hour": 12,
    "Dry-bulb": 21.1,
    "Dew Point": 6.7,
    "RH": 39
  },
  {
    "Year": 1977,
    "Month": 1,
    "Day": 24,
    "Hour": 13,
    "Dry-bulb": 22.2,
    "Dew Point": 6.1,
    "RH": 35
  },
  {
    "Year": 1977,
    "Month": 1,
    "Day": 24,
    "Hour": 14,
    "Dry-bulb": 22.8,
    "Dew Point": 5.6,
    "RH": 33
  },
  {
    "Year": 1977,
    "Month": 1,
    "Day": 24,
    "Hour": 15,
    "Dry-bulb": 21.1,
    "Dew Point": 8.9,
    "RH": 46
  },
  {
    "Year": 1977,
    "Month": 1,
    "Day": 24,
    "Hour": 16,
    "Dry-bulb": 20,
    "Dew Point": 10.6,
    "RH": 55
  },
  {
    "Year": 1977,
    "Month": 1,
    "Day": 24,
    "Hour": 17,
    "Dry-bulb": 18.3,
    "Dew Point": 7.8,
    "RH": 50
  },
  {
    "Year": 1977,
    "Month": 1,
    "Day": 24,
    "Hour": 18,
    "Dry-bulb": 16.7,
    "Dew Point": 6.1,
    "RH": 50
  },
  {
    "Year": 1977,
    "Month": 1,
    "Day": 24,
    "Hour": 19,
    "Dry-bulb": 17.2,
    "Dew Point": 8.3,
    "RH": 56
  },
  {
    "Year": 1977,
    "Month": 1,
    "Day": 24,
    "Hour": 20,
    "Dry-bulb": 17.2,
    "Dew Point": 6.1,
    "RH": 48
  },
  {
    "Year": 1977,
    "Month": 1,
    "Day": 24,
    "Hour": 21,
    "Dry-bulb": 16.7,
    "Dew Point": 4.4,
    "RH": 45
  },
  {
    "Year": 1977,
    "Month": 1,
    "Day": 24,
    "Hour": 22,
    "Dry-bulb": 15.6,
    "Dew Point": 5.6,
    "RH": 52
  },
  {
    "Year": 1977,
    "Month": 1,
    "Day": 24,
    "Hour": 23,
    "Dry-bulb": 15.6,
    "Dew Point": 5,
    "RH": 50
  },
  {
    "Year": 1977,
    "Month": 1,
    "Day": 24,
    "Hour": 24,
    "Dry-bulb": 15.6,
    "Dew Point": 4.4,
    "RH": 48
  },
  {
    "Year": 1977,
    "Month": 1,
    "Day": 25,
    "Hour": 1,
    "Dry-bulb": 14.4,
    "Dew Point": 3.9,
    "RH": 49
  },
  {
    "Year": 1977,
    "Month": 1,
    "Day": 25,
    "Hour": 2,
    "Dry-bulb": 14.4,
    "Dew Point": 3.3,
    "RH": 48
  },
  {
    "Year": 1977,
    "Month": 1,
    "Day": 25,
    "Hour": 3,
    "Dry-bulb": 14.4,
    "Dew Point": 3.3,
    "RH": 48
  },
  {
    "Year": 1977,
    "Month": 1,
    "Day": 25,
    "Hour": 4,
    "Dry-bulb": 12.8,
    "Dew Point": 3.9,
    "RH": 55
  },
  {
    "Year": 1977,
    "Month": 1,
    "Day": 25,
    "Hour": 5,
    "Dry-bulb": 12.8,
    "Dew Point": 2.8,
    "RH": 51
  },
  {
    "Year": 1977,
    "Month": 1,
    "Day": 25,
    "Hour": 6,
    "Dry-bulb": 13.9,
    "Dew Point": 2.8,
    "RH": 47
  },
  {
    "Year": 1977,
    "Month": 1,
    "Day": 25,
    "Hour": 7,
    "Dry-bulb": 13.9,
    "Dew Point": 2.8,
    "RH": 47
  },
  {
    "Year": 1977,
    "Month": 1,
    "Day": 25,
    "Hour": 8,
    "Dry-bulb": 13.9,
    "Dew Point": 3.3,
    "RH": 49
  },
  {
    "Year": 1977,
    "Month": 1,
    "Day": 25,
    "Hour": 9,
    "Dry-bulb": 14.4,
    "Dew Point": 4.4,
    "RH": 51
  },
  {
    "Year": 1977,
    "Month": 1,
    "Day": 25,
    "Hour": 10,
    "Dry-bulb": 15,
    "Dew Point": 4.4,
    "RH": 50
  },
  {
    "Year": 1977,
    "Month": 1,
    "Day": 25,
    "Hour": 11,
    "Dry-bulb": 17.2,
    "Dew Point": 5,
    "RH": 45
  },
  {
    "Year": 1977,
    "Month": 1,
    "Day": 25,
    "Hour": 12,
    "Dry-bulb": 18.9,
    "Dew Point": 4.4,
    "RH": 39
  },
  {
    "Year": 1977,
    "Month": 1,
    "Day": 25,
    "Hour": 13,
    "Dry-bulb": 20,
    "Dew Point": 5.6,
    "RH": 39
  },
  {
    "Year": 1977,
    "Month": 1,
    "Day": 25,
    "Hour": 14,
    "Dry-bulb": 21.1,
    "Dew Point": 5,
    "RH": 35
  },
  {
    "Year": 1977,
    "Month": 1,
    "Day": 25,
    "Hour": 15,
    "Dry-bulb": 19.4,
    "Dew Point": 6.1,
    "RH": 42
  },
  {
    "Year": 1977,
    "Month": 1,
    "Day": 25,
    "Hour": 16,
    "Dry-bulb": 18.3,
    "Dew Point": 6.7,
    "RH": 47
  },
  {
    "Year": 1977,
    "Month": 1,
    "Day": 25,
    "Hour": 17,
    "Dry-bulb": 17.8,
    "Dew Point": 7.2,
    "RH": 50
  },
  {
    "Year": 1977,
    "Month": 1,
    "Day": 25,
    "Hour": 18,
    "Dry-bulb": 16.7,
    "Dew Point": 8.3,
    "RH": 58
  },
  {
    "Year": 1977,
    "Month": 1,
    "Day": 25,
    "Hour": 19,
    "Dry-bulb": 17.2,
    "Dew Point": 8.9,
    "RH": 58
  },
  {
    "Year": 1977,
    "Month": 1,
    "Day": 25,
    "Hour": 20,
    "Dry-bulb": 16.7,
    "Dew Point": 7.2,
    "RH": 54
  },
  {
    "Year": 1977,
    "Month": 1,
    "Day": 25,
    "Hour": 21,
    "Dry-bulb": 16.7,
    "Dew Point": 8.3,
    "RH": 58
  },
  {
    "Year": 1977,
    "Month": 1,
    "Day": 25,
    "Hour": 22,
    "Dry-bulb": 16.7,
    "Dew Point": 11.7,
    "RH": 73
  },
  {
    "Year": 1977,
    "Month": 1,
    "Day": 25,
    "Hour": 23,
    "Dry-bulb": 16.1,
    "Dew Point": 9.4,
    "RH": 65
  },
  {
    "Year": 1977,
    "Month": 1,
    "Day": 25,
    "Hour": 24,
    "Dry-bulb": 15.6,
    "Dew Point": 9.4,
    "RH": 67
  },
  {
    "Year": 1977,
    "Month": 1,
    "Day": 26,
    "Hour": 1,
    "Dry-bulb": 15,
    "Dew Point": 8.3,
    "RH": 65
  },
  {
    "Year": 1977,
    "Month": 1,
    "Day": 26,
    "Hour": 2,
    "Dry-bulb": 15,
    "Dew Point": 8.3,
    "RH": 65
  },
  {
    "Year": 1977,
    "Month": 1,
    "Day": 26,
    "Hour": 3,
    "Dry-bulb": 15,
    "Dew Point": 8.3,
    "RH": 65
  },
  {
    "Year": 1977,
    "Month": 1,
    "Day": 26,
    "Hour": 4,
    "Dry-bulb": 14.4,
    "Dew Point": 8.9,
    "RH": 70
  },
  {
    "Year": 1977,
    "Month": 1,
    "Day": 26,
    "Hour": 5,
    "Dry-bulb": 13.3,
    "Dew Point": 8.3,
    "RH": 72
  },
  {
    "Year": 1977,
    "Month": 1,
    "Day": 26,
    "Hour": 6,
    "Dry-bulb": 12.8,
    "Dew Point": 8.3,
    "RH": 75
  },
  {
    "Year": 1977,
    "Month": 1,
    "Day": 26,
    "Hour": 7,
    "Dry-bulb": 12.2,
    "Dew Point": 8.3,
    "RH": 77
  },
  {
    "Year": 1977,
    "Month": 1,
    "Day": 26,
    "Hour": 8,
    "Dry-bulb": 13.3,
    "Dew Point": 8.3,
    "RH": 72
  },
  {
    "Year": 1977,
    "Month": 1,
    "Day": 26,
    "Hour": 9,
    "Dry-bulb": 15,
    "Dew Point": 8.3,
    "RH": 65
  },
  {
    "Year": 1977,
    "Month": 1,
    "Day": 26,
    "Hour": 10,
    "Dry-bulb": 16.7,
    "Dew Point": 9.4,
    "RH": 63
  },
  {
    "Year": 1977,
    "Month": 1,
    "Day": 26,
    "Hour": 11,
    "Dry-bulb": 18.3,
    "Dew Point": 10,
    "RH": 59
  },
  {
    "Year": 1977,
    "Month": 1,
    "Day": 26,
    "Hour": 12,
    "Dry-bulb": 18.9,
    "Dew Point": 9.4,
    "RH": 54
  },
  {
    "Year": 1977,
    "Month": 1,
    "Day": 26,
    "Hour": 13,
    "Dry-bulb": 19.4,
    "Dew Point": 10.6,
    "RH": 57
  },
  {
    "Year": 1977,
    "Month": 1,
    "Day": 26,
    "Hour": 14,
    "Dry-bulb": 18.9,
    "Dew Point": 11.1,
    "RH": 61
  },
  {
    "Year": 1977,
    "Month": 1,
    "Day": 26,
    "Hour": 15,
    "Dry-bulb": 18.9,
    "Dew Point": 10.6,
    "RH": 59
  },
  {
    "Year": 1977,
    "Month": 1,
    "Day": 26,
    "Hour": 16,
    "Dry-bulb": 17.2,
    "Dew Point": 12.8,
    "RH": 75
  },
  {
    "Year": 1977,
    "Month": 1,
    "Day": 26,
    "Hour": 17,
    "Dry-bulb": 16.7,
    "Dew Point": 12.8,
    "RH": 78
  },
  {
    "Year": 1977,
    "Month": 1,
    "Day": 26,
    "Hour": 18,
    "Dry-bulb": 15.6,
    "Dew Point": 12.8,
    "RH": 84
  },
  {
    "Year": 1977,
    "Month": 1,
    "Day": 26,
    "Hour": 19,
    "Dry-bulb": 15,
    "Dew Point": 12.8,
    "RH": 87
  },
  {
    "Year": 1977,
    "Month": 1,
    "Day": 26,
    "Hour": 20,
    "Dry-bulb": 14.4,
    "Dew Point": 12.8,
    "RH": 90
  },
  {
    "Year": 1977,
    "Month": 1,
    "Day": 26,
    "Hour": 21,
    "Dry-bulb": 14.4,
    "Dew Point": 13.3,
    "RH": 93
  },
  {
    "Year": 1977,
    "Month": 1,
    "Day": 26,
    "Hour": 22,
    "Dry-bulb": 14.4,
    "Dew Point": 11.1,
    "RH": 81
  },
  {
    "Year": 1977,
    "Month": 1,
    "Day": 26,
    "Hour": 23,
    "Dry-bulb": 14.4,
    "Dew Point": 9.4,
    "RH": 72
  },
  {
    "Year": 1977,
    "Month": 1,
    "Day": 26,
    "Hour": 24,
    "Dry-bulb": 12.8,
    "Dew Point": 9.4,
    "RH": 80
  },
  {
    "Year": 1977,
    "Month": 1,
    "Day": 27,
    "Hour": 1,
    "Dry-bulb": 12.2,
    "Dew Point": 9.4,
    "RH": 83
  },
  {
    "Year": 1977,
    "Month": 1,
    "Day": 27,
    "Hour": 2,
    "Dry-bulb": 11.7,
    "Dew Point": 9.4,
    "RH": 86
  },
  {
    "Year": 1977,
    "Month": 1,
    "Day": 27,
    "Hour": 3,
    "Dry-bulb": 11.1,
    "Dew Point": 8.3,
    "RH": 83
  },
  {
    "Year": 1977,
    "Month": 1,
    "Day": 27,
    "Hour": 4,
    "Dry-bulb": 11.1,
    "Dew Point": 8.3,
    "RH": 83
  },
  {
    "Year": 1977,
    "Month": 1,
    "Day": 27,
    "Hour": 5,
    "Dry-bulb": 11.1,
    "Dew Point": 8.3,
    "RH": 83
  },
  {
    "Year": 1977,
    "Month": 1,
    "Day": 27,
    "Hour": 6,
    "Dry-bulb": 11.1,
    "Dew Point": 7.8,
    "RH": 80
  },
  {
    "Year": 1977,
    "Month": 1,
    "Day": 27,
    "Hour": 7,
    "Dry-bulb": 11.1,
    "Dew Point": 7.8,
    "RH": 80
  },
  {
    "Year": 1977,
    "Month": 1,
    "Day": 27,
    "Hour": 8,
    "Dry-bulb": 11.7,
    "Dew Point": 7.8,
    "RH": 77
  },
  {
    "Year": 1977,
    "Month": 1,
    "Day": 27,
    "Hour": 9,
    "Dry-bulb": 13.3,
    "Dew Point": 8.9,
    "RH": 75
  },
  {
    "Year": 1977,
    "Month": 1,
    "Day": 27,
    "Hour": 10,
    "Dry-bulb": 15.6,
    "Dew Point": 9.4,
    "RH": 67
  },
  {
    "Year": 1977,
    "Month": 1,
    "Day": 27,
    "Hour": 11,
    "Dry-bulb": 17.2,
    "Dew Point": 10,
    "RH": 63
  },
  {
    "Year": 1977,
    "Month": 1,
    "Day": 27,
    "Hour": 12,
    "Dry-bulb": 18.3,
    "Dew Point": 9.4,
    "RH": 56
  },
  {
    "Year": 1977,
    "Month": 1,
    "Day": 27,
    "Hour": 13,
    "Dry-bulb": 18.3,
    "Dew Point": 8.9,
    "RH": 54
  },
  {
    "Year": 1977,
    "Month": 1,
    "Day": 27,
    "Hour": 14,
    "Dry-bulb": 18.3,
    "Dew Point": 12.2,
    "RH": 68
  },
  {
    "Year": 1977,
    "Month": 1,
    "Day": 27,
    "Hour": 15,
    "Dry-bulb": 18.9,
    "Dew Point": 12.8,
    "RH": 68
  },
  {
    "Year": 1977,
    "Month": 1,
    "Day": 27,
    "Hour": 16,
    "Dry-bulb": 18.3,
    "Dew Point": 12.2,
    "RH": 68
  },
  {
    "Year": 1977,
    "Month": 1,
    "Day": 27,
    "Hour": 17,
    "Dry-bulb": 16.1,
    "Dew Point": 12.8,
    "RH": 81
  },
  {
    "Year": 1977,
    "Month": 1,
    "Day": 27,
    "Hour": 18,
    "Dry-bulb": 16.1,
    "Dew Point": 13.9,
    "RH": 87
  },
  {
    "Year": 1977,
    "Month": 1,
    "Day": 27,
    "Hour": 19,
    "Dry-bulb": 15.6,
    "Dew Point": 13.9,
    "RH": 90
  },
  {
    "Year": 1977,
    "Month": 1,
    "Day": 27,
    "Hour": 20,
    "Dry-bulb": 15.6,
    "Dew Point": 13.3,
    "RH": 87
  },
  {
    "Year": 1977,
    "Month": 1,
    "Day": 27,
    "Hour": 21,
    "Dry-bulb": 15.6,
    "Dew Point": 13.9,
    "RH": 90
  },
  {
    "Year": 1977,
    "Month": 1,
    "Day": 27,
    "Hour": 22,
    "Dry-bulb": 15,
    "Dew Point": 12.8,
    "RH": 87
  },
  {
    "Year": 1977,
    "Month": 1,
    "Day": 27,
    "Hour": 23,
    "Dry-bulb": 15,
    "Dew Point": 13.9,
    "RH": 93
  },
  {
    "Year": 1977,
    "Month": 1,
    "Day": 27,
    "Hour": 24,
    "Dry-bulb": 15,
    "Dew Point": 13.9,
    "RH": 93
  },
  {
    "Year": 1977,
    "Month": 1,
    "Day": 28,
    "Hour": 1,
    "Dry-bulb": 15,
    "Dew Point": 13.9,
    "RH": 93
  },
  {
    "Year": 1977,
    "Month": 1,
    "Day": 28,
    "Hour": 2,
    "Dry-bulb": 15,
    "Dew Point": 14.4,
    "RH": 97
  },
  {
    "Year": 1977,
    "Month": 1,
    "Day": 28,
    "Hour": 3,
    "Dry-bulb": 15,
    "Dew Point": 14.4,
    "RH": 97
  },
  {
    "Year": 1977,
    "Month": 1,
    "Day": 28,
    "Hour": 4,
    "Dry-bulb": 15,
    "Dew Point": 13.9,
    "RH": 93
  },
  {
    "Year": 1977,
    "Month": 1,
    "Day": 28,
    "Hour": 5,
    "Dry-bulb": 14.4,
    "Dew Point": 13.9,
    "RH": 96
  },
  {
    "Year": 1977,
    "Month": 1,
    "Day": 28,
    "Hour": 6,
    "Dry-bulb": 14.4,
    "Dew Point": 13.9,
    "RH": 96
  },
  {
    "Year": 1977,
    "Month": 1,
    "Day": 28,
    "Hour": 7,
    "Dry-bulb": 14.4,
    "Dew Point": 13.3,
    "RH": 93
  },
  {
    "Year": 1977,
    "Month": 1,
    "Day": 28,
    "Hour": 8,
    "Dry-bulb": 14.4,
    "Dew Point": 13.9,
    "RH": 96
  },
  {
    "Year": 1977,
    "Month": 1,
    "Day": 28,
    "Hour": 9,
    "Dry-bulb": 14.4,
    "Dew Point": 13.3,
    "RH": 93
  },
  {
    "Year": 1977,
    "Month": 1,
    "Day": 28,
    "Hour": 10,
    "Dry-bulb": 15.6,
    "Dew Point": 13.9,
    "RH": 90
  },
  {
    "Year": 1977,
    "Month": 1,
    "Day": 28,
    "Hour": 11,
    "Dry-bulb": 17.2,
    "Dew Point": 12.2,
    "RH": 73
  },
  {
    "Year": 1977,
    "Month": 1,
    "Day": 28,
    "Hour": 12,
    "Dry-bulb": 17.2,
    "Dew Point": 14.4,
    "RH": 84
  },
  {
    "Year": 1977,
    "Month": 1,
    "Day": 28,
    "Hour": 13,
    "Dry-bulb": 16.1,
    "Dew Point": 14.4,
    "RH": 90
  },
  {
    "Year": 1977,
    "Month": 1,
    "Day": 28,
    "Hour": 14,
    "Dry-bulb": 16.1,
    "Dew Point": 13.9,
    "RH": 87
  },
  {
    "Year": 1977,
    "Month": 1,
    "Day": 28,
    "Hour": 15,
    "Dry-bulb": 15.6,
    "Dew Point": 13.9,
    "RH": 90
  },
  {
    "Year": 1977,
    "Month": 1,
    "Day": 28,
    "Hour": 16,
    "Dry-bulb": 15.6,
    "Dew Point": 14.4,
    "RH": 93
  },
  {
    "Year": 1977,
    "Month": 1,
    "Day": 28,
    "Hour": 17,
    "Dry-bulb": 15,
    "Dew Point": 13.9,
    "RH": 93
  },
  {
    "Year": 1977,
    "Month": 1,
    "Day": 28,
    "Hour": 18,
    "Dry-bulb": 15,
    "Dew Point": 13.9,
    "RH": 93
  },
  {
    "Year": 1977,
    "Month": 1,
    "Day": 28,
    "Hour": 19,
    "Dry-bulb": 14.4,
    "Dew Point": 13.3,
    "RH": 93
  },
  {
    "Year": 1977,
    "Month": 1,
    "Day": 28,
    "Hour": 20,
    "Dry-bulb": 14.4,
    "Dew Point": 12.2,
    "RH": 87
  },
  {
    "Year": 1977,
    "Month": 1,
    "Day": 28,
    "Hour": 21,
    "Dry-bulb": 14.4,
    "Dew Point": 12.2,
    "RH": 87
  },
  {
    "Year": 1977,
    "Month": 1,
    "Day": 28,
    "Hour": 22,
    "Dry-bulb": 13.9,
    "Dew Point": 12.2,
    "RH": 90
  },
  {
    "Year": 1977,
    "Month": 1,
    "Day": 28,
    "Hour": 23,
    "Dry-bulb": 12.8,
    "Dew Point": 12.2,
    "RH": 96
  },
  {
    "Year": 1977,
    "Month": 1,
    "Day": 28,
    "Hour": 24,
    "Dry-bulb": 12.8,
    "Dew Point": 12.2,
    "RH": 96
  },
  {
    "Year": 1977,
    "Month": 1,
    "Day": 29,
    "Hour": 1,
    "Dry-bulb": 12.2,
    "Dew Point": 11.7,
    "RH": 96
  },
  {
    "Year": 1977,
    "Month": 1,
    "Day": 29,
    "Hour": 2,
    "Dry-bulb": 12.2,
    "Dew Point": 11.7,
    "RH": 96
  },
  {
    "Year": 1977,
    "Month": 1,
    "Day": 29,
    "Hour": 3,
    "Dry-bulb": 12.2,
    "Dew Point": 11.7,
    "RH": 96
  },
  {
    "Year": 1977,
    "Month": 1,
    "Day": 29,
    "Hour": 4,
    "Dry-bulb": 11.7,
    "Dew Point": 11.1,
    "RH": 96
  },
  {
    "Year": 1977,
    "Month": 1,
    "Day": 29,
    "Hour": 5,
    "Dry-bulb": 11.1,
    "Dew Point": 10.6,
    "RH": 96
  },
  {
    "Year": 1977,
    "Month": 1,
    "Day": 29,
    "Hour": 6,
    "Dry-bulb": 11.1,
    "Dew Point": 10,
    "RH": 93
  },
  {
    "Year": 1977,
    "Month": 1,
    "Day": 29,
    "Hour": 7,
    "Dry-bulb": 11.1,
    "Dew Point": 10.6,
    "RH": 96
  },
  {
    "Year": 1977,
    "Month": 1,
    "Day": 29,
    "Hour": 8,
    "Dry-bulb": 11.1,
    "Dew Point": 10,
    "RH": 93
  },
  {
    "Year": 1977,
    "Month": 1,
    "Day": 29,
    "Hour": 9,
    "Dry-bulb": 11.7,
    "Dew Point": 10.6,
    "RH": 93
  },
  {
    "Year": 1977,
    "Month": 1,
    "Day": 29,
    "Hour": 10,
    "Dry-bulb": 14.4,
    "Dew Point": 12.8,
    "RH": 90
  },
  {
    "Year": 1977,
    "Month": 1,
    "Day": 29,
    "Hour": 11,
    "Dry-bulb": 15.6,
    "Dew Point": 13.3,
    "RH": 87
  },
  {
    "Year": 1977,
    "Month": 1,
    "Day": 29,
    "Hour": 12,
    "Dry-bulb": 17.8,
    "Dew Point": 14.4,
    "RH": 81
  },
  {
    "Year": 1977,
    "Month": 1,
    "Day": 29,
    "Hour": 13,
    "Dry-bulb": 17.8,
    "Dew Point": 13.3,
    "RH": 75
  },
  {
    "Year": 1977,
    "Month": 1,
    "Day": 29,
    "Hour": 14,
    "Dry-bulb": 17.8,
    "Dew Point": 14.4,
    "RH": 81
  },
  {
    "Year": 1977,
    "Month": 1,
    "Day": 29,
    "Hour": 15,
    "Dry-bulb": 17.8,
    "Dew Point": 14.4,
    "RH": 81
  },
  {
    "Year": 1977,
    "Month": 1,
    "Day": 29,
    "Hour": 16,
    "Dry-bulb": 17.2,
    "Dew Point": 14.4,
    "RH": 84
  },
  {
    "Year": 1977,
    "Month": 1,
    "Day": 29,
    "Hour": 17,
    "Dry-bulb": 16.1,
    "Dew Point": 13.9,
    "RH": 87
  },
  {
    "Year": 1977,
    "Month": 1,
    "Day": 29,
    "Hour": 18,
    "Dry-bulb": 14.4,
    "Dew Point": 13.3,
    "RH": 93
  },
  {
    "Year": 1977,
    "Month": 1,
    "Day": 29,
    "Hour": 19,
    "Dry-bulb": 14.4,
    "Dew Point": 13.3,
    "RH": 93
  },
  {
    "Year": 1977,
    "Month": 1,
    "Day": 29,
    "Hour": 20,
    "Dry-bulb": 13.9,
    "Dew Point": 13.3,
    "RH": 96
  },
  {
    "Year": 1977,
    "Month": 1,
    "Day": 29,
    "Hour": 21,
    "Dry-bulb": 13.9,
    "Dew Point": 13.3,
    "RH": 96
  },
  {
    "Year": 1977,
    "Month": 1,
    "Day": 29,
    "Hour": 22,
    "Dry-bulb": 13.9,
    "Dew Point": 13.3,
    "RH": 96
  },
  {
    "Year": 1977,
    "Month": 1,
    "Day": 29,
    "Hour": 23,
    "Dry-bulb": 12.8,
    "Dew Point": 12.2,
    "RH": 96
  },
  {
    "Year": 1977,
    "Month": 1,
    "Day": 29,
    "Hour": 24,
    "Dry-bulb": 12.2,
    "Dew Point": 12.2,
    "RH": 100
  },
  {
    "Year": 1977,
    "Month": 1,
    "Day": 30,
    "Hour": 1,
    "Dry-bulb": 11.7,
    "Dew Point": 11.7,
    "RH": 100
  },
  {
    "Year": 1977,
    "Month": 1,
    "Day": 30,
    "Hour": 2,
    "Dry-bulb": 11.7,
    "Dew Point": 11.1,
    "RH": 96
  },
  {
    "Year": 1977,
    "Month": 1,
    "Day": 30,
    "Hour": 3,
    "Dry-bulb": 11.1,
    "Dew Point": 11.1,
    "RH": 100
  },
  {
    "Year": 1977,
    "Month": 1,
    "Day": 30,
    "Hour": 4,
    "Dry-bulb": 10.6,
    "Dew Point": 10.6,
    "RH": 100
  },
  {
    "Year": 1977,
    "Month": 1,
    "Day": 30,
    "Hour": 5,
    "Dry-bulb": 9.4,
    "Dew Point": 8.9,
    "RH": 96
  },
  {
    "Year": 1977,
    "Month": 1,
    "Day": 30,
    "Hour": 6,
    "Dry-bulb": 8.9,
    "Dew Point": 8.9,
    "RH": 100
  },
  {
    "Year": 1977,
    "Month": 1,
    "Day": 30,
    "Hour": 7,
    "Dry-bulb": 8.9,
    "Dew Point": 8.9,
    "RH": 100
  },
  {
    "Year": 1977,
    "Month": 1,
    "Day": 30,
    "Hour": 8,
    "Dry-bulb": 8.9,
    "Dew Point": 8.9,
    "RH": 100
  },
  {
    "Year": 1977,
    "Month": 1,
    "Day": 30,
    "Hour": 9,
    "Dry-bulb": 12.8,
    "Dew Point": 10.6,
    "RH": 86
  },
  {
    "Year": 1977,
    "Month": 1,
    "Day": 30,
    "Hour": 10,
    "Dry-bulb": 15,
    "Dew Point": 13.3,
    "RH": 90
  },
  {
    "Year": 1977,
    "Month": 1,
    "Day": 30,
    "Hour": 11,
    "Dry-bulb": 17.8,
    "Dew Point": 13.9,
    "RH": 78
  },
  {
    "Year": 1977,
    "Month": 1,
    "Day": 30,
    "Hour": 12,
    "Dry-bulb": 18.9,
    "Dew Point": 13.3,
    "RH": 70
  },
  {
    "Year": 1977,
    "Month": 1,
    "Day": 30,
    "Hour": 13,
    "Dry-bulb": 19.4,
    "Dew Point": 13.9,
    "RH": 70
  },
  {
    "Year": 1977,
    "Month": 1,
    "Day": 30,
    "Hour": 14,
    "Dry-bulb": 18.3,
    "Dew Point": 14.4,
    "RH": 78
  },
  {
    "Year": 1977,
    "Month": 1,
    "Day": 30,
    "Hour": 15,
    "Dry-bulb": 18.3,
    "Dew Point": 14.4,
    "RH": 78
  },
  {
    "Year": 1977,
    "Month": 1,
    "Day": 30,
    "Hour": 16,
    "Dry-bulb": 18.3,
    "Dew Point": 12.8,
    "RH": 70
  },
  {
    "Year": 1977,
    "Month": 1,
    "Day": 30,
    "Hour": 17,
    "Dry-bulb": 17.8,
    "Dew Point": 13.9,
    "RH": 78
  },
  {
    "Year": 1977,
    "Month": 1,
    "Day": 30,
    "Hour": 18,
    "Dry-bulb": 15.6,
    "Dew Point": 13.3,
    "RH": 87
  },
  {
    "Year": 1977,
    "Month": 1,
    "Day": 30,
    "Hour": 19,
    "Dry-bulb": 15,
    "Dew Point": 13.9,
    "RH": 93
  },
  {
    "Year": 1977,
    "Month": 1,
    "Day": 30,
    "Hour": 20,
    "Dry-bulb": 15,
    "Dew Point": 13.9,
    "RH": 93
  },
  {
    "Year": 1977,
    "Month": 1,
    "Day": 30,
    "Hour": 21,
    "Dry-bulb": 14.4,
    "Dew Point": 13.9,
    "RH": 96
  },
  {
    "Year": 1977,
    "Month": 1,
    "Day": 30,
    "Hour": 22,
    "Dry-bulb": 13.9,
    "Dew Point": 13.3,
    "RH": 96
  },
  {
    "Year": 1977,
    "Month": 1,
    "Day": 30,
    "Hour": 23,
    "Dry-bulb": 12.8,
    "Dew Point": 12.2,
    "RH": 96
  },
  {
    "Year": 1977,
    "Month": 1,
    "Day": 30,
    "Hour": 24,
    "Dry-bulb": 12.8,
    "Dew Point": 12.2,
    "RH": 96
  },
  {
    "Year": 1977,
    "Month": 1,
    "Day": 31,
    "Hour": 1,
    "Dry-bulb": 11.7,
    "Dew Point": 11.1,
    "RH": 96
  },
  {
    "Year": 1977,
    "Month": 1,
    "Day": 31,
    "Hour": 2,
    "Dry-bulb": 10.6,
    "Dew Point": 10,
    "RH": 96
  },
  {
    "Year": 1977,
    "Month": 1,
    "Day": 31,
    "Hour": 3,
    "Dry-bulb": 9.4,
    "Dew Point": 6.7,
    "RH": 83
  },
  {
    "Year": 1977,
    "Month": 1,
    "Day": 31,
    "Hour": 4,
    "Dry-bulb": 8.3,
    "Dew Point": 6.7,
    "RH": 89
  },
  {
    "Year": 1977,
    "Month": 1,
    "Day": 31,
    "Hour": 5,
    "Dry-bulb": 7.8,
    "Dew Point": 5.6,
    "RH": 86
  },
  {
    "Year": 1977,
    "Month": 1,
    "Day": 31,
    "Hour": 6,
    "Dry-bulb": 7.8,
    "Dew Point": 5,
    "RH": 83
  },
  {
    "Year": 1977,
    "Month": 1,
    "Day": 31,
    "Hour": 7,
    "Dry-bulb": 11.7,
    "Dew Point": 3.9,
    "RH": 59
  },
  {
    "Year": 1977,
    "Month": 1,
    "Day": 31,
    "Hour": 8,
    "Dry-bulb": 12.2,
    "Dew Point": 3.9,
    "RH": 57
  },
  {
    "Year": 1977,
    "Month": 1,
    "Day": 31,
    "Hour": 9,
    "Dry-bulb": 11.7,
    "Dew Point": 11.7,
    "RH": 100
  },
  {
    "Year": 1977,
    "Month": 1,
    "Day": 31,
    "Hour": 10,
    "Dry-bulb": 13.3,
    "Dew Point": 12.8,
    "RH": 96
  },
  {
    "Year": 1977,
    "Month": 1,
    "Day": 31,
    "Hour": 11,
    "Dry-bulb": 16.7,
    "Dew Point": 11.1,
    "RH": 70
  },
  {
    "Year": 1977,
    "Month": 1,
    "Day": 31,
    "Hour": 12,
    "Dry-bulb": 18.3,
    "Dew Point": 10.6,
    "RH": 61
  },
  {
    "Year": 1977,
    "Month": 1,
    "Day": 31,
    "Hour": 13,
    "Dry-bulb": 20,
    "Dew Point": 12.8,
    "RH": 63
  },
  {
    "Year": 1977,
    "Month": 1,
    "Day": 31,
    "Hour": 14,
    "Dry-bulb": 18.9,
    "Dew Point": 14.4,
    "RH": 76
  },
  {
    "Year": 1977,
    "Month": 1,
    "Day": 31,
    "Hour": 15,
    "Dry-bulb": 18.3,
    "Dew Point": 14.4,
    "RH": 78
  },
  {
    "Year": 1977,
    "Month": 1,
    "Day": 31,
    "Hour": 16,
    "Dry-bulb": 17.2,
    "Dew Point": 14.4,
    "RH": 84
  },
  {
    "Year": 1977,
    "Month": 1,
    "Day": 31,
    "Hour": 17,
    "Dry-bulb": 15.6,
    "Dew Point": 13.9,
    "RH": 90
  },
  {
    "Year": 1977,
    "Month": 1,
    "Day": 31,
    "Hour": 18,
    "Dry-bulb": 14.4,
    "Dew Point": 13.3,
    "RH": 93
  },
  {
    "Year": 1977,
    "Month": 1,
    "Day": 31,
    "Hour": 19,
    "Dry-bulb": 13.3,
    "Dew Point": 12.8,
    "RH": 96
  },
  {
    "Year": 1977,
    "Month": 1,
    "Day": 31,
    "Hour": 20,
    "Dry-bulb": 13.3,
    "Dew Point": 12.8,
    "RH": 96
  },
  {
    "Year": 1977,
    "Month": 1,
    "Day": 31,
    "Hour": 21,
    "Dry-bulb": 13.3,
    "Dew Point": 12.8,
    "RH": 96
  },
  {
    "Year": 1977,
    "Month": 1,
    "Day": 31,
    "Hour": 22,
    "Dry-bulb": 13,
    "Dew Point": 12.4,
    "RH": 96
  },
  {
    "Year": 1977,
    "Month": 1,
    "Day": 31,
    "Hour": 23,
    "Dry-bulb": 12.7,
    "Dew Point": 12,
    "RH": 96
  },
  {
    "Year": 1977,
    "Month": 1,
    "Day": 31,
    "Hour": 24,
    "Dry-bulb": 12.4,
    "Dew Point": 11.6,
    "RH": 96
  }
]
}